[{"no":"1","name":"คอนกรีตผสมเสร็จรูปลูกบาศก์ 180 กก./ตร.ซม. และรูปทรงกระบอก 140 กก./ตร.ซม.","unit":"ลบ.ม.","jan":"2,000.00","feb":"2,000.00","mar":"2,000.00","apr":"2,000.00","may":"2,000.00","jun":"1,929.91","jul":"1,929.91","aug":"1,929.91","sept":"-","oct":"-","nov":"-","dec":"-","average":"1,973.72"},{"no":"2","name":"คอนกรีตผสมเสร็จรูปลูกบาศก์ 210 กก./ตร.ซม. และรูปทรงกระบอก 180 กก./ตร.ซม.","unit":"ลบ.ม.","jan":"2,050.47","feb":"2,050.47","mar":"2,050.47","apr":"2,050.47","may":"2,050.47","jun":"1,979.44","jul":"1,979.44","aug":"1,979.44","sept":"-","oct":"-","nov":"-","dec":"-","average":"2,023.83"},{"no":"3","name":"คอนกรีตผสมเสร็จรูปลูกบาศก์ 240 กก./ตร.ซม. และรูปทรงกระบอก 210 กก./ตร.ซม.","unit":"ลบ.ม.","jan":"2,100.00","feb":"2,100.00","mar":"2,100.00","apr":"2,100.00","may":"2,100.00","jun":"2,029.91","jul":"2,029.91","aug":"2,029.91","sept":"-","oct":"-","nov":"-","dec":"-","average":"2,073.72"},{"no":"4","name":"คอนกรีตผสมเสร็จรูปลูกบาศก์ 280 กก./ตร.ซม. และรูปทรงกระบอก 240 กก./ตร.ซม .","unit":"ลบ.ม.","jan":"2,289.72","feb":"2,289.72","mar":"2,289.72","apr":"2,289.72","may":"2,289.72","jun":"2,289.72","jul":"2,289.72","aug":"2,139.25","sept":"-","oct":"-","nov":"-","dec":"-","average":"2,270.91"},{"no":"5","name":"คอนกรีตบล็อกก่อผนัง ชนิดธรรมดา ขนาด 19 x 39 x 7 ซม.","unit":"ก้อน","jan":"7.01","feb":"7.01","mar":"7.01","apr":"7.01","may":"7.01","jun":"7.01","jul":"7.01","aug":"6.78","sept":"-","oct":"-","nov":"-","dec":"-","average":"6.98"},{"no":"6","name":"เหล็กเส้นกลมผิวเรียบ SR.24 ยาว 10 เมตร ศก. 6 มม.","unit":"ตัน","jan":"30,426.64","feb":"30,636.92","mar":"30,636.92","apr":"30,636.92","may":"31,480.84","jun":"32,625.72","jul":"32,625.72","aug":"31,101.77","sept":"-","oct":"-","nov":"-","dec":"-","average":"31,271.43"},{"no":"7","name":"เหล็กเส้นกลมผิวเรียบ SR.24 ยาว 10 เมตร ศก. 9 มม.","unit":"ตัน","jan":"29,224.45","feb":"29,411.69","mar":"29,411.69","apr":"29,411.69","may":"30,349.07","jun":"31,464.49","jul":"31,464.49","aug":"29,886.53","sept":"-","oct":"-","nov":"-","dec":"-","average":"30,078.01"},{"no":"8","name":"เหล็กเส้นกลมผิวเรียบ SR.24 ยาว 10 เมตร ศก. 12 มม.","unit":"ตัน","jan":"28,053.27","feb":"28,379.91","mar":"29,408.41","apr":"29,408.41","may":"30,514.96","jun":"29,297.67","jul":"29,297.67","aug":"26,484.05","sept":"-","oct":"-","nov":"-","dec":"-","average":"28,855.54"},{"no":"9","name":"เหล็กเส้นกลมผิวเรียบ SR.24 ยาว 10 เมตร ศก. 15 มม.","unit":"ตัน","jan":"28,620.57","feb":"29,118.23","mar":"30,146.27","apr":"30,146.27","may":"31,669.16","jun":"30,450.98","jul":"30,450.98","aug":"28,319.05","sept":"-","oct":"-","nov":"-","dec":"-","average":"29,865.19"},{"no":"10","name":"เหล็กเส้นกลมผิวเรียบ SR.24 ยาว 10 เมตร ศก. 19 มม.","unit":"ตัน","jan":"25,271.24","feb":"25,807.95","mar":"26,835.99","apr":"26,835.99","may":"28,100.00","jun":"27,092.25","jul":"27,092.25","aug":"25,197.63","sept":"-","oct":"-","nov":"-","dec":"-","average":"26,529.16"},{"no":"11","name":"เหล็กเส้นกลมผิวข้ออ้อย SD.40 ยาว 10 เมตร ศก. 12 มม.","unit":"ตัน","jan":"27,492.53","feb":"28,082.71","mar":"29,064.02","apr":"29,064.02","may":"30,430.84","jun":"29,420.57","jul":"29,420.57","aug":"25,651.35","sept":"-","oct":"-","nov":"-","dec":"-","average":"28,578.33"},{"no":"12","name":"เหล็กเส้นกลมผิวข้ออ้อย SD.40 ยาว 10 เมตร ศก. 16 มม.","unit":"ตัน","jan":"26,308.47","feb":"26,782.71","mar":"27,764.02","apr":"27,764.02","may":"29,639.25","jun":"29,034.58","jul":"29,034.58","aug":"25,363.76","sept":"-","oct":"-","nov":"-","dec":"-","average":"27,711.42"},{"no":"13","name":"เหล็กเส้นกลมผิวข้ออ้อย SD.40 ยาว 10 เมตร ศก. 20 มม.","unit":"ตัน","jan":"25,297.66","feb":"25,814.49","mar":"26,795.80","apr":"26,795.80","may":"28,115.89","jun":"27,457.95","jul":"27,457.95","aug":"24,417.65","sept":"-","oct":"-","nov":"-","dec":"-","average":"26,519.15"},{"no":"14","name":"เหล็กเส้นกลมผิวข้ออ้อย SD.40 ยาว 10 เมตร ศก. 25 มม.","unit":"ตัน","jan":"29,557.63","feb":"30,794.86","mar":"31,776.17","apr":"31,776.17","may":"33,345.33","jun":"33,688.79","jul":"33,688.79","aug":"31,025.63","sept":"-","oct":"-","nov":"-","dec":"-","average":"31,956.67"},{"no":"15","name":"ลวดผูกเหล็ก ศก. 1.25 มม. (เบอร์ 18)","unit":"กก.","jan":"39.72","feb":"39.72","mar":"39.72","apr":"39.72","may":"44.39","jun":"53.74","jul":"53.74","aug":"42.06","sept":"-","oct":"-","nov":"-","dec":"-","average":"44.10"},{"no":"16","name":"เหล็กฉาก หนา 4 มม. ยาว 6 เมตร ขนาด 50 x 50 มม. น้ำหนัก 18.4 กก.","unit":"ท่อน","jan":"574.77","feb":"574.77","mar":"574.77","apr":"574.77","may":"574.77","jun":"574.77","jul":"579.44","aug":"579.44","sept":"-","oct":"-","nov":"-","dec":"-","average":"575.94"},{"no":"17","name":"เหล็กฉาก หนา 6 มม. ยาว 6 เมตร ขนาด 50 x 50 มม. น้ำหนัก 26.8 กก.","unit":"ท่อน","jan":"783.18","feb":"783.18","mar":"783.18","apr":"783.18","may":"783.18","jun":"783.18","jul":"788.32","aug":"788.32","sept":"-","oct":"-","nov":"-","dec":"-","average":"784.47"},{"no":"18","name":"เหล็กฉาก หนา 6 มม. ยาว 6 เมตร ขนาด 75 x 75 มม. น้ำหนัก 41.1 กก.","unit":"ท่อน","jan":"1,398.13","feb":"1,398.13","mar":"1,398.13","apr":"1,398.13","may":"1,398.13","jun":"1,422.90","jul":"1,430.37","aug":"1,430.37","sept":"-","oct":"-","nov":"-","dec":"-","average":"1,409.29"},{"no":"19","name":"เหล็กตัวซี (Light Lip Channel Steel) หนา 2.3 มม. ยาว 6 เมตร ขนาด 100 x 50 x 20 มม. น้ำหนัก 23.5 กก.","unit":"ท่อน","jan":"789.72","feb":"789.72","mar":"789.72","apr":"789.72","may":"789.72","jun":"831.78","jul":"831.78","aug":"789.72","sept":"-","oct":"-","nov":"-","dec":"-","average":"800.24"},{"no":"20","name":"เหล็กตัวซี (Light Lip Channel Steel) หนา 2.3 มม. ยาว 6 เมตร ขนาด 125 x 50 x 20 มม. น้ำหนัก 25.5 กก.","unit":"ท่อน","jan":"890.19","feb":"890.19","mar":"890.19","apr":"890.19","may":"890.19","jun":"890.19","jul":"890.19","aug":"890.19","sept":"-","oct":"-","nov":"-","dec":"-","average":"890.19"},{"no":"21","name":"เหล็กตัวซี (Light Lip Channel Steel) หนา 3.2 มม. ยาว 6 เมตร ขนาด 125 x 50 x 20 มม. น้ำหนัก 36.5 กก.","unit":"ท่อน","jan":"1,186.45","feb":"1,186.45","mar":"1,186.45","apr":"1,186.45","may":"1,186.45","jun":"1,186.45","jul":"1,209.81","aug":"1,209.81","sept":"-","oct":"-","nov":"-","dec":"-","average":"1,192.29"},{"no":"22","name":"เหล็กตัวซี (Light Lip Channel Steel) หนา 2.3 มม. ยาว 6 เมตร ขนาด 150 x 50 x 20 มม. น้ำหนัก 29.5 กก.","unit":"ท่อน","jan":"1,002.34","feb":"1,002.34","mar":"1,002.34","apr":"1,002.34","may":"1,002.34","jun":"1,002.34","jul":"1,002.34","aug":"1,002.34","sept":"-","oct":"-","nov":"-","dec":"-","average":"1,002.34"},{"no":"23","name":"เหล็กตัวซี (Light Lip Channel Steel) หนา 3.2 มม. ยาว 6 เมตร ขนาด 150 x 50 x 20 มม. น้ำหนัก 40.3 กก.","unit":"ท่อน","jan":"1,160.75","feb":"1,160.75","mar":"1,160.75","apr":"1,160.75","may":"1,160.75","jun":"1,160.75","jul":"1,305.61","aug":"1,305.61","sept":"-","oct":"-","nov":"-","dec":"-","average":"1,196.97"},{"no":"24","name":"ท่อเหล็กกลวงสี่เหลี่ยมจัตุรัส หนา 1.2 มม. ขนาด 1/2\" x 1/2\" ยาว 6 เมตร","unit":"ท่อน","jan":"149.53","feb":"149.53","mar":"149.53","apr":"149.53","may":"163.55","jun":"163.55","jul":"161.68","aug":"157.01","sept":"-","oct":"-","nov":"-","dec":"-","average":"155.49"},{"no":"25","name":"ท่อเหล็กกลวงสี่เหลี่ยมจัตุรัส หนา 1.2 มม. ขนาด 3/4\" x 3/4\" ยาว 6 เมตร","unit":"ท่อน","jan":"168.22","feb":"168.22","mar":"168.22","apr":"168.22","may":"182.24","jun":"182.24","jul":"177.57","aug":"175.00","sept":"-","oct":"-","nov":"-","dec":"-","average":"173.74"},{"no":"26","name":"ท่อเหล็กกลวงสี่เหลี่ยมจัตุรัส หนา 1.2 มม. ขนาด 1\" x 1\" ยาว 6 เมตร","unit":"ท่อน","jan":"228.97","feb":"233.64","mar":"233.64","apr":"233.64","may":"238.32","jun":"238.32","jul":"242.99","aug":"230.00","sept":"-","oct":"-","nov":"-","dec":"-","average":"234.94"},{"no":"27","name":"ท่อเหล็กกลวงสี่เหลี่ยมจัตุรัส หนา 2.0 มม. ขนาด 2\" x 2\" ยาว 6 เมตร","unit":"ท่อน","jan":"640.19","feb":"649.53","mar":"649.53","apr":"649.53","may":"658.88","jun":"658.88","jul":"658.88","aug":"650.00","sept":"-","oct":"-","nov":"-","dec":"-","average":"651.93"},{"no":"28","name":"ท่อเหล็กกลวงสี่เหลี่ยมจัตุรัส หนา 2.0 มม. ขนาด 3\" x 3\" ยาว 6 เมตร","unit":"ท่อน","jan":"1,009.35","feb":"1,028.04","mar":"1,028.04","apr":"1,028.04","may":"1,056.07","jun":"1,168.22","jul":"1,168.22","aug":"1,180.00","sept":"-","oct":"-","nov":"-","dec":"-","average":"1,083.25"},{"no":"29","name":"ท่อเหล็กกลวงสี่เหลี่ยมจัตุรัส หนา 1.2 มม. ขนาด 1 1/2\" x 1 1/2\" ยาว 6 เมตร","unit":"ท่อน","jan":"411.21","feb":"420.56","mar":"420.56","apr":"420.56","may":"429.91","jun":"429.91","jul":"420.56","aug":"420.00","sept":"-","oct":"-","nov":"-","dec":"-","average":"421.66"},{"no":"30","name":"ท่อเหล็กเคลือบสังกะสี รวมข้อต่อตรง 1 อัน ประเภท BS-M ยาว 6 เมตร ศก. 1/2 นิ้ว","unit":"ท่อน","jan":"303.74","feb":"303.74","mar":"303.74","apr":"303.74","may":"278.04","jun":"310.75","jul":"308.42","aug":"269.32","sept":"-","oct":"-","nov":"-","dec":"-","average":"297.69"},{"no":"31","name":"ท่อเหล็กเคลือบสังกะสี รวมข้อต่อตรง 1 อัน ประเภท BS-M ยาว 6 เมตร ศก. 3/4 นิ้ว","unit":"ท่อน","jan":"380.84","feb":"380.84","mar":"380.84","apr":"380.84","may":"366.83","jun":"406.55","jul":"406.55","aug":"361.52","sept":"-","oct":"-","nov":"-","dec":"-","average":"383.10"},{"no":"32","name":"ท่อเหล็กเคลือบสังกะสี รวมข้อต่อตรง 1 อัน ประเภท BS-M ยาว 6 เมตร ศก. 1นิ้ว","unit":"ท่อน","jan":"521.03","feb":"521.03","mar":"521.03","apr":"521.03","may":"490.66","jun":"511.68","jul":"511.68","aug":"487.26","sept":"-","oct":"-","nov":"-","dec":"-","average":"510.68"},{"no":"33","name":"ท่อเหล็กเคลือบสังกะสี รวมข้อต่อตรง 1 อัน ประเภท BS-M ยาว 6 เมตร ศก. 2 นิ้ว","unit":"ท่อน","jan":"1,056.07","feb":"1,056.07","mar":"1,056.07","apr":"1,056.07","may":"1,056.07","jun":"1,074.77","jul":"1,074.77","aug":"1,072.00","sept":"-","oct":"-","nov":"-","dec":"-","average":"1,062.74"},{"no":"34","name":"ท่อเหล็กเคลือบสังกะสี รวมข้อต่อตรง 1 อัน ประเภท BS-M ยาว 6 เมตร ศก. 2 1/2 นิ้ว","unit":"ท่อน","jan":"1,261.68","feb":"1,261.68","mar":"1,261.68","apr":"1,261.68","may":"1,205.61","jun":"1,233.64","jul":"1,233.64","aug":"1,362.62","sept":"-","oct":"-","nov":"-","dec":"-","average":"1,260.28"},{"no":"35","name":"ท่อเหล็กเคลือบสังกะสี รวมข้อต่อตรง 1 อัน ประเภท BS-M ยาว 6 เมตร ศก. 3 นิ้ว","unit":"ท่อน","jan":"1,588.79","feb":"1,588.79","mar":"1,588.79","apr":"1,588.79","may":"1,523.36","jun":"1,542.06","jul":"1,542.06","aug":"1,530.00","sept":"-","oct":"-","nov":"-","dec":"-","average":"1,561.58"},{"no":"36","name":"ข้อต่อตรงเหล็ก ศก. 1/2 นิ้ว","unit":"อัน","jan":"12.15","feb":"12.15","mar":"12.15","apr":"12.15","may":"12.15","jun":"14.95","jul":"14.95","aug":"14.95","sept":"-","oct":"-","nov":"-","dec":"-","average":"13.20"},{"no":"37","name":"ข้อต่อตรงเหล็ก ศก. 3/4 นิ้ว","unit":"อัน","jan":"16.82","feb":"16.82","mar":"16.82","apr":"16.82","may":"16.82","jun":"20.56","jul":"20.56","aug":"20.56","sept":"-","oct":"-","nov":"-","dec":"-","average":"18.22"},{"no":"38","name":"ข้อต่อตรงเหล็ก ศก. 1 นิ้ว","unit":"อัน","jan":"28.04","feb":"28.04","mar":"28.04","apr":"28.04","may":"28.04","jun":"35.51","jul":"35.51","aug":"35.51","sept":"-","oct":"-","nov":"-","dec":"-","average":"30.84"},{"no":"39","name":"ข้อต่องอเหล็ก 90 องศา ศก. 1/2 นิ้ว","unit":"อัน","jan":"14.02","feb":"14.02","mar":"14.02","apr":"14.02","may":"14.02","jun":"16.82","jul":"16.82","aug":"16.82","sept":"-","oct":"-","nov":"-","dec":"-","average":"15.07"},{"no":"40","name":"ข้อต่องอเหล็ก 90 องศา ศก. 3/4 นิ้ว","unit":"อัน","jan":"19.63","feb":"19.63","mar":"19.63","apr":"19.63","may":"19.63","jun":"25.23","jul":"25.23","aug":"25.23","sept":"-","oct":"-","nov":"-","dec":"-","average":"21.73"},{"no":"41","name":"ข้อต่องอเหล็ก 90 องศา ศก. 1 นิ้ว","unit":"อัน","jan":"30.84","feb":"30.84","mar":"30.84","apr":"30.84","may":"30.84","jun":"42.99","jul":"42.99","aug":"42.99","sept":"-","oct":"-","nov":"-","dec":"-","average":"35.40"},{"no":"42","name":"สามทาง 90 องศาเหล็กเคลือบสังกะสี ศก. 1/2 นิ้ว","unit":"อัน","jan":"19.63","feb":"19.63","mar":"19.63","apr":"19.63","may":"19.63","jun":"27.10","jul":"27.10","aug":"27.10","sept":"-","oct":"-","nov":"-","dec":"-","average":"22.43"},{"no":"43","name":"สามทาง 90 องศาเหล็กเคลือบสังกะสี ศก. 3/4 นิ้ว","unit":"อัน","jan":"28.04","feb":"28.04","mar":"28.04","apr":"28.04","may":"28.04","jun":"32.71","jul":"32.71","aug":"32.71","sept":"-","oct":"-","nov":"-","dec":"-","average":"29.79"},{"no":"44","name":"สามทาง 90 องศาเหล็กเคลือบสังกะสี ศก. 1 นิ้ว","unit":"อัน","jan":"46.73","feb":"46.73","mar":"46.73","apr":"46.73","may":"46.73","jun":"54.21","jul":"54.21","aug":"54.21","sept":"-","oct":"-","nov":"-","dec":"-","average":"49.54"},{"no":"45","name":"ท่อ พีวีซี แข็ง ท่อประปา ชนิดปลายธรรมดา ชั้น 8.5 ยาว 4 เมตร เส้นผ่านศูนย์กลาง 1/2\" ตราท่อน้ำไทย","unit":"ท่อน","jan":"51.40","feb":"51.40","mar":"51.40","apr":"51.40","may":"51.40","jun":"51.40","jul":"51.40","aug":"50.47","sept":"-","oct":"-","nov":"-","dec":"-","average":"51.28"},{"no":"46","name":"ท่อ พีวีซี แข็ง ท่อประปา ชนิดปลายธรรมดา ชั้น 8.5 ยาว 4 เมตร เส้นผ่านศูนย์กลาง 3/4\" ตราท่อน้ำไทย","unit":"ท่อน","jan":"63.55","feb":"63.55","mar":"63.55","apr":"63.55","may":"63.55","jun":"63.55","jul":"63.55","aug":"63.55","sept":"-","oct":"-","nov":"-","dec":"-","average":"63.55"},{"no":"47","name":"ท่อ พีวีซี แข็ง ท่อประปา ชนิดปลายธรรมดา ชั้น 8.5 ยาว 4 เมตร เส้นผ่านศูนย์กลาง 1\" ตราท่อน้ำไทย","unit":"ท่อน","jan":"84.11","feb":"84.11","mar":"84.11","apr":"84.11","may":"84.11","jun":"84.11","jul":"84.11","aug":"84.11","sept":"-","oct":"-","nov":"-","dec":"-","average":"84.11"},{"no":"48","name":"ท่อ พีวีซี แข็ง ท่อประปา ชนิดปลายธรรมดา ชั้น 8.5 ยาว 4 เมตร เส้นผ่านศูนย์กลาง 1 1/2\" ตราท่อน้ำไทย","unit":"ท่อน","jan":"137.38","feb":"137.38","mar":"137.38","apr":"137.38","may":"137.38","jun":"137.38","jul":"137.38","aug":"137.38","sept":"-","oct":"-","nov":"-","dec":"-","average":"137.38"},{"no":"49","name":"ท่อ พีวีซี แข็ง ท่อประปา ชนิดปลายธรรมดา ชั้น 8.5 ยาว 4 เมตร เส้นผ่านศูนย์กลาง 2\" ตราท่อน้ำไทย","unit":"ท่อน","jan":"215.89","feb":"215.89","mar":"215.89","apr":"215.89","may":"215.89","jun":"215.89","jul":"215.89","aug":"215.89","sept":"-","oct":"-","nov":"-","dec":"-","average":"215.89"},{"no":"50","name":"ท่อ พีวีซี แข็ง ท่อประปา ชนิดปลายธรรมดา ชั้น 8.5 ยาว 4 เมตร เส้นผ่านศูนย์กลาง 2 1/2\" ตราท่อน้ำไทย","unit":"ท่อน","jan":"342.06","feb":"342.06","mar":"342.06","apr":"342.06","may":"342.06","jun":"342.06","jul":"342.06","aug":"342.06","sept":"-","oct":"-","nov":"-","dec":"-","average":"342.06"},{"no":"51","name":"ท่อ พีวีซี แข็ง ท่อประปา ชนิดปลายธรรมดา ชั้น 8.5 ยาว 4 เมตร เส้นผ่านศูนย์กลาง 3\" ตราท่อน้ำไทย","unit":"ท่อน","jan":"473.83","feb":"473.83","mar":"473.83","apr":"473.83","may":"473.83","jun":"473.83","jul":"473.83","aug":"473.83","sept":"-","oct":"-","nov":"-","dec":"-","average":"473.83"},{"no":"52","name":"ท่อ พีวีซี แข็ง ท่อประปา ชนิดปลายธรรมดา ชั้น 8.5 ยาว 4 เมตร เส้นผ่านศูนย์กลาง 4\" ตราท่อน้ำไทย","unit":"ท่อน","jan":"768.22","feb":"768.22","mar":"768.22","apr":"768.22","may":"768.22","jun":"768.22","jul":"768.22","aug":"768.22","sept":"-","oct":"-","nov":"-","dec":"-","average":"768.22"},{"no":"53","name":"ท่อ พีวีซี แข็ง ท่อประปา ชนิดปลายธรรมดา ชั้น 8.5 ยาว 4 เมตร เส้นผ่านศูนย์กลาง 5\" ตราท่อน้ำไทย","unit":"ท่อน","jan":"1,159.81","feb":"1,159.81","mar":"1,159.81","apr":"1,159.81","may":"1,159.81","jun":"1,159.81","jul":"1,159.81","aug":"1,159.81","sept":"-","oct":"-","nov":"-","dec":"-","average":"1,159.81"},{"no":"54","name":"ท่อ พีวีซี แข็ง ท่อประปา ชนิดปลายธรรมดา ชั้น 8.5 ยาว 4 เมตร เส้นผ่านศูนย์กลาง 6\" ตราท่อน้ำไทย","unit":"ท่อน","jan":"1,629.91","feb":"1,629.91","mar":"1,629.91","apr":"1,629.91","may":"1,629.91","jun":"1,629.91","jul":"1,629.91","aug":"1,629.91","sept":"-","oct":"-","nov":"-","dec":"-","average":"1,629.91"},{"no":"55","name":"ท่อ พีวีซี แข็ง ท่อประปา ชนิดปลายธรรมดา ชั้น 8.5 ยาว 4 เมตร เส้นผ่านศูนย์กลาง 8\" ตราท่อน้ำไทย","unit":"ท่อน","jan":"2,619.63","feb":"2,619.63","mar":"2,619.63","apr":"2,619.63","may":"2,619.63","jun":"2,619.63","jul":"2,619.63","aug":"2,619.63","sept":"-","oct":"-","nov":"-","dec":"-","average":"2,619.63"},{"no":"56","name":"ท่อ พีวีซี แข็ง ท่อประปา ชนิดปลายธรรมดา ชั้น 8.5 ยาว 4 เมตร เส้นผ่านศูนย์กลาง 10\" ตราท่อน้ำไทย","unit":"ท่อน","jan":"3,789.72","feb":"3,789.72","mar":"3,789.72","apr":"3,789.72","may":"3,789.72","jun":"3,789.72","jul":"3,789.72","aug":"3,789.72","sept":"-","oct":"-","nov":"-","dec":"-","average":"3,789.72"},{"no":"57","name":"ท่อ พีวีซี แข็ง ท่อประปา ชนิดปลายธรรมดา ชั้น 8.5 ยาว 4 เมตร เส้นผ่านศูนย์กลาง 1\" ตราเสือ","unit":"ท่อน","jan":"102.80","feb":"112.15","mar":"112.15","apr":"112.15","may":"110.28","jun":"112.15","jul":"112.15","aug":"107.48","sept":"-","oct":"-","nov":"-","dec":"-","average":"110.16"},{"no":"58","name":"ท่อ พีวีซี แข็ง ท่อประปา ชนิดปลายธรรมดา ชั้น 8.5 ยาว 4 เมตร เส้นผ่านศูนย์กลาง 1 1/2\" ตราเสือ","unit":"ท่อน","jan":"168.22","feb":"177.57","mar":"177.57","apr":"177.57","may":"172.90","jun":"177.57","jul":"177.57","aug":"168.22","sept":"-","oct":"-","nov":"-","dec":"-","average":"174.65"},{"no":"59","name":"ท่อ พีวีซี แข็ง ท่อประปา ชนิดปลายธรรมดา ชั้น 8.5 ยาว 4 เมตร เส้นผ่านศูนย์กลาง 3\" ตราเสือ","unit":"ท่อน","jan":"364.49","feb":"373.83","mar":"373.83","apr":"373.83","may":"364.49","jun":"364.49","jul":"355.14","aug":"345.79","sept":"-","oct":"-","nov":"-","dec":"-","average":"364.49"},{"no":"60","name":"ท่อ พีวีซี แข็ง ท่อประปา ชนิดปลายธรรมดา ชั้น 8.5 ยาว 4 เมตร เส้นผ่านศูนย์กลาง 4\" ตราเสือ","unit":"ท่อน","jan":"598.13","feb":"616.82","mar":"616.82","apr":"616.82","may":"607.48","jun":"607.48","jul":"598.13","aug":"579.44","sept":"-","oct":"-","nov":"-","dec":"-","average":"605.14"},{"no":"61","name":"ท่อ พีวีซี แข็ง ท่อประปา ชนิดปลายธรรมดา ชั้น 13.5 ยาว 4 เมตร เส้นผ่านศูนย์กลาง 1/2\" ตราท่อน้ำไทย","unit":"ท่อน","jan":"59.35","feb":"58.88","mar":"59.81","apr":"59.81","may":"60.28","jun":"59.81","jul":"59.81","aug":"58.88","sept":"-","oct":"-","nov":"-","dec":"-","average":"59.58"},{"no":"62","name":"ท่อ พีวีซี แข็ง ท่อประปา ชนิดปลายธรรมดา ชั้น 13.5 ยาว 4 เมตร เส้นผ่านศูนย์กลาง 3/4\" ตราท่อน้ำไทย","unit":"ท่อน","jan":"71.50","feb":"71.03","mar":"71.97","apr":"71.97","may":"72.90","jun":"71.97","jul":"71.97","aug":"71.50","sept":"-","oct":"-","nov":"-","dec":"-","average":"71.85"},{"no":"63","name":"ท่อ พีวีซี แข็ง ท่อประปา ชนิดปลายธรรมดา ชั้น 13.5 ยาว 4 เมตร เส้นผ่านศูนย์กลาง 1\" ตราท่อน้ำไทย","unit":"ท่อน","jan":"112.62","feb":"111.22","mar":"113.09","apr":"113.09","may":"114.96","jun":"113.09","jul":"113.09","aug":"112.15","sept":"-","oct":"-","nov":"-","dec":"-","average":"112.91"},{"no":"64","name":"ท่อ พีวีซี แข็ง ท่อประปา ชนิดปลายธรรมดา ชั้น 13.5 ยาว 4 เมตร เส้นผ่านศูนย์กลาง 1 1/4\" ตราท่อน้ำไทย","unit":"ท่อน","jan":"158.88","feb":"158.88","mar":"158.88","apr":"158.88","may":"158.88","jun":"158.88","jul":"158.88","aug":"158.88","sept":"-","oct":"-","nov":"-","dec":"-","average":"158.88"},{"no":"65","name":"ท่อ พีวีซี แข็ง ท่อประปา ชนิดปลายธรรมดา ชั้น 13.5 ยาว 4 เมตร เส้นผ่านศูนย์กลาง 1 1/2\" ตราท่อน้ำไทย","unit":"ท่อน","jan":"203.74","feb":"203.74","mar":"203.74","apr":"203.74","may":"203.74","jun":"203.74","jul":"203.74","aug":"203.74","sept":"-","oct":"-","nov":"-","dec":"-","average":"203.74"},{"no":"66","name":"ท่อ พีวีซี แข็ง ท่อประปา ชนิดปลายธรรมดา ชั้น 13.5 ยาว 4 เมตร เส้นผ่านศูนย์กลาง 2\" ตราท่อน้ำไทย","unit":"ท่อน","jan":"319.63","feb":"319.63","mar":"319.63","apr":"319.63","may":"319.63","jun":"312.15","jul":"312.15","aug":"312.15","sept":"-","oct":"-","nov":"-","dec":"-","average":"316.83"},{"no":"67","name":"ท่อ พีวีซี แข็ง ท่อประปา ชนิดปลายธรรมดา ชั้น 13.5 ยาว 4 เมตร เส้นผ่านศูนย์กลาง 2 1/2\" ตราท่อน้ำไทย","unit":"ท่อน","jan":"515.89","feb":"515.89","mar":"515.89","apr":"515.89","may":"515.89","jun":"515.89","jul":"515.89","aug":"515.89","sept":"-","oct":"-","nov":"-","dec":"-","average":"515.89"},{"no":"68","name":"ท่อ พีวีซี แข็ง ท่อประปา ชนิดปลายธรรมดา ชั้น 13.5 ยาว 4 เมตร เส้นผ่านศูนย์กลาง 3\" ตราท่อน้ำไทย","unit":"ท่อน","jan":"719.63","feb":"719.63","mar":"719.63","apr":"719.63","may":"719.63","jun":"719.63","jul":"719.63","aug":"719.63","sept":"-","oct":"-","nov":"-","dec":"-","average":"719.63"},{"no":"69","name":"ท่อ พีวีซี แข็ง ท่อประปา ชนิดปลายธรรมดา ชั้น 13.5 ยาว 4 เมตร เส้นผ่านศูนย์กลาง 4\" ตราท่อน้ำไทย","unit":"ท่อน","jan":"1,159.81","feb":"1,159.81","mar":"1,159.81","apr":"1,159.81","may":"1,159.81","jun":"1,159.81","jul":"1,159.81","aug":"1,159.81","sept":"-","oct":"-","nov":"-","dec":"-","average":"1,159.81"},{"no":"70","name":"ท่อ พีวีซี แข็ง ท่อประปา ชนิดปลายธรรมดา ชั้น 13.5 ยาว 4 เมตร เส้นผ่านศูนย์กลาง 5\" ตราท่อน้ำไทย","unit":"ท่อน","jan":"1,750.47","feb":"1,750.47","mar":"1,750.47","apr":"1,750.47","may":"1,750.47","jun":"1,750.47","jul":"1,750.47","aug":"1,750.47","sept":"-","oct":"-","nov":"-","dec":"-","average":"1,750.47"},{"no":"71","name":"ท่อ พีวีซี แข็ง ท่อประปา ชนิดปลายธรรมดา ชั้น 13.5 ยาว 4 เมตร เส้นผ่านศูนย์กลาง 6\" ตราท่อน้ำไทย","unit":"ท่อน","jan":"2,459.81","feb":"2,459.81","mar":"2,459.81","apr":"2,459.81","may":"2,459.81","jun":"2,459.81","jul":"2,459.81","aug":"2,459.81","sept":"-","oct":"-","nov":"-","dec":"-","average":"2,459.81"},{"no":"72","name":"ท่อ พีวีซี แข็ง ท่อประปา ชนิดปลายธรรมดา ชั้น 13.5 ยาว 4 เมตร เส้นผ่านศูนย์กลาง 8\" ตราท่อน้ำไทย","unit":"ท่อน","jan":"4,189.72","feb":"4,189.72","mar":"4,189.72","apr":"4,189.72","may":"4,189.72","jun":"4,189.72","jul":"4,189.72","aug":"4,189.72","sept":"-","oct":"-","nov":"-","dec":"-","average":"4,189.72"},{"no":"73","name":"ท่อ พีวีซี แข็ง ท่อประปา ชนิดปลายธรรมดา ชั้น 13.5 ยาว 4 เมตร เส้นผ่านศูนย์กลาง 10\" ตราท่อน้ำไทย","unit":"ท่อน","jan":"6,300.00","feb":"6,300.00","mar":"6,300.00","apr":"6,300.00","may":"6,300.00","jun":"6,300.00","jul":"6,300.00","aug":"6,300.00","sept":"-","oct":"-","nov":"-","dec":"-","average":"6,300.00"},{"no":"74","name":"ท่อ พีวีซี แข็ง ท่อประปา ชนิดปลายธรรมดา ชั้น 13.5 ยาว 4 เมตร เส้นผ่านศูนย์กลาง 14\" ตราท่อน้ำไทย","unit":"ท่อน","jan":"6,369.16","feb":"6,369.16","mar":"6,369.16","apr":"6,369.16","may":"6,369.16","jun":"6,369.16","jul":"6,369.16","aug":"-","sept":"-","oct":"-","nov":"-","dec":"-","average":"6,369.16"},{"no":"75","name":"ท่อ พีวีซี แข็ง ท่อประปา ชนิดปลายธรรมดา ชั้น 13.5 ยาว 4 เมตร เส้นผ่านศูนย์กลาง 1/2\" ตราเสือ","unit":"ท่อน","jan":"78.50","feb":"82.24","mar":"82.24","apr":"82.24","may":"82.24","jun":"82.24","jul":"81.31","aug":"79.44","sept":"-","oct":"-","nov":"-","dec":"-","average":"81.31"},{"no":"76","name":"ท่อ พีวีซี แข็ง ท่อประปา ชนิดปลายธรรมดา ชั้น 13.5 ยาว 4 เมตร เส้นผ่านศูนย์กลาง 3/4\" ตราเสือ","unit":"ท่อน","jan":"88.79","feb":"93.46","mar":"93.46","apr":"93.46","may":"90.65","jun":"90.65","jul":"88.79","aug":"86.92","sept":"-","oct":"-","nov":"-","dec":"-","average":"90.77"},{"no":"77","name":"ท่อ พีวีซี แข็ง ท่อประปา ชนิดปลายธรรมดา ชั้น 13.5 ยาว 4 เมตร เส้นผ่านศูนย์กลาง 1\" ตราเสือ","unit":"ท่อน","jan":"98.13","feb":"107.48","mar":"107.48","apr":"107.48","may":"105.61","jun":"108.41","jul":"102.80","aug":"100.00","sept":"-","oct":"-","nov":"-","dec":"-","average":"104.67"},{"no":"78","name":"ข้อต่อท่อ พีวีซี ตรง สำหรับใช้กับท่อรับแรงดัน เส้นผ่านศูนย์กลาง 1/2\" ตราท่อน้ำไทย","unit":"อัน","jan":"4.36","feb":"4.36","mar":"4.36","apr":"4.36","may":"4.36","jun":"4.99","jul":"4.99","aug":"4.99","sept":"-","oct":"-","nov":"-","dec":"-","average":"4.60"},{"no":"79","name":"ข้อต่อท่อ พีวีซี ตรง สำหรับใช้กับท่อรับแรงดัน เส้นผ่านศูนย์กลาง 3/4\" ตราท่อน้ำไทย","unit":"อัน","jan":"5.29","feb":"5.29","mar":"5.29","apr":"5.29","may":"5.29","jun":"6.23","jul":"6.23","aug":"6.23","sept":"-","oct":"-","nov":"-","dec":"-","average":"5.64"},{"no":"80","name":"ข้อต่อท่อ พีวีซี ตรง สำหรับใช้กับท่อรับแรงดัน เส้นผ่านศูนย์กลาง 1\" ตราท่อน้ำไทย","unit":"อัน","jan":"8.10","feb":"8.10","mar":"8.10","apr":"8.10","may":"8.10","jun":"9.66","jul":"9.66","aug":"9.66","sept":"-","oct":"-","nov":"-","dec":"-","average":"8.69"},{"no":"81","name":"ข้อต่อท่อ พีวีซี ตรง สำหรับใช้กับท่อรับแรงดัน เส้นผ่านศูนย์กลาง 1 1/4\" ตราท่อน้ำไทย","unit":"อัน","jan":"12.62","feb":"12.62","mar":"12.62","apr":"12.62","may":"12.62","jun":"12.62","jul":"12.62","aug":"12.62","sept":"-","oct":"-","nov":"-","dec":"-","average":"12.62"},{"no":"82","name":"ข้อต่อท่อ พีวีซี ตรง สำหรับใช้กับท่อรับแรงดัน เส้นผ่านศูนย์กลาง 1 1/2\" ตราท่อน้ำไทย","unit":"อัน","jan":"15.42","feb":"15.42","mar":"15.42","apr":"15.42","may":"15.42","jun":"15.42","jul":"15.42","aug":"15.42","sept":"-","oct":"-","nov":"-","dec":"-","average":"15.42"},{"no":"83","name":"ข้อต่อท่อ พีวีซี ตรง สำหรับใช้กับท่อรับแรงดัน เส้นผ่านศูนย์กลาง 2\" ตราท่อน้ำไทย","unit":"อัน","jan":"22.90","feb":"22.90","mar":"22.90","apr":"22.90","may":"22.90","jun":"22.90","jul":"22.90","aug":"22.90","sept":"-","oct":"-","nov":"-","dec":"-","average":"22.90"},{"no":"84","name":"ข้อต่อท่อ พีวีซี ตรง สำหรับใช้กับท่อรับแรงดัน เส้นผ่านศูนย์กลาง 2 1/2\" ตราท่อน้ำไทย","unit":"อัน","jan":"40.19","feb":"40.19","mar":"40.19","apr":"40.19","may":"40.19","jun":"40.19","jul":"40.19","aug":"40.19","sept":"-","oct":"-","nov":"-","dec":"-","average":"40.19"},{"no":"85","name":"ข้อต่อท่อ พีวีซี ตรง สำหรับใช้กับท่อรับแรงดัน เส้นผ่านศูนย์กลาง 3\" ตราท่อน้ำไทย","unit":"อัน","jan":"56.07","feb":"56.07","mar":"56.07","apr":"56.07","may":"56.07","jun":"56.07","jul":"56.07","aug":"56.07","sept":"-","oct":"-","nov":"-","dec":"-","average":"56.07"},{"no":"86","name":"ข้อต่อท่อ พีวีซี ตรง สำหรับใช้กับท่อรับแรงดัน เส้นผ่านศูนย์กลาง 4\" ตราท่อน้ำไทย","unit":"อัน","jan":"104.67","feb":"104.67","mar":"104.67","apr":"104.67","may":"104.67","jun":"105.61","jul":"105.61","aug":"105.61","sept":"-","oct":"-","nov":"-","dec":"-","average":"105.02"},{"no":"87","name":"ข้อต่อท่อ พีวีซี ตรง สำหรับใช้กับท่อรับแรงดัน เส้นผ่านศูนย์กลาง 1/2\" ตราเสือ","unit":"อัน","jan":"6.54","feb":"6.54","mar":"6.54","apr":"6.54","may":"6.54","jun":"6.54","jul":"6.54","aug":"6.54","sept":"-","oct":"-","nov":"-","dec":"-","average":"6.54"},{"no":"88","name":"ข้อต่อท่อ พีวีซี ตรง สำหรับใช้กับท่อรับแรงดัน เส้นผ่านศูนย์กลาง 3/4\" ตราเสือ","unit":"อัน","jan":"8.41","feb":"9.35","mar":"9.35","apr":"9.35","may":"10.28","jun":"10.28","jul":"9.35","aug":"9.35","sept":"-","oct":"-","nov":"-","dec":"-","average":"9.47"},{"no":"89","name":"ข้อต่อท่อ พีวีซี ตรง สำหรับใช้กับท่อรับแรงดัน เส้นผ่านศูนย์กลาง 1\" ตราเสือ","unit":"อัน","jan":"14.02","feb":"14.02","mar":"14.02","apr":"14.02","may":"14.95","jun":"14.95","jul":"14.02","aug":"14.02","sept":"-","oct":"-","nov":"-","dec":"-","average":"14.25"},{"no":"90","name":"ข้อต่อท่อ พีวีซี ข้องอ 90 องศา สำหรับใช้กับท่อรับแรงดัน เส้นผ่านศูนย์กลาง 1/2\" ตราท่อน้ำไทย","unit":"อัน","jan":"4.98","feb":"4.98","mar":"4.98","apr":"4.98","may":"4.98","jun":"5.61","jul":"5.61","aug":"5.61","sept":"-","oct":"-","nov":"-","dec":"-","average":"5.22"},{"no":"91","name":"ข้อต่อท่อ พีวีซี ข้องอ 90 องศา สำหรับใช้กับท่อรับแรงดัน เส้นผ่านศูนย์กลาง 3/4\" ตราท่อน้ำไทย","unit":"อัน","jan":"5.92","feb":"5.92","mar":"5.92","apr":"5.92","may":"5.92","jun":"6.86","jul":"6.86","aug":"6.86","sept":"-","oct":"-","nov":"-","dec":"-","average":"6.27"},{"no":"92","name":"ข้อต่อท่อ พีวีซี ข้องอ 90 องศา สำหรับใช้กับท่อรับแรงดัน เส้นผ่านศูนย์กลาง 1\" ตราท่อน้ำไทย","unit":"อัน","jan":"9.66","feb":"9.66","mar":"9.66","apr":"9.66","may":"9.66","jun":"12.46","jul":"12.46","aug":"12.46","sept":"-","oct":"-","nov":"-","dec":"-","average":"10.71"},{"no":"93","name":"ข้อต่อท่อ พีวีซี ข้องอ 90 องศา สำหรับใช้กับท่อรับแรงดัน เส้นผ่านศูนย์กลาง 1 1/4\" ตราท่อน้ำไทย","unit":"อัน","jan":"17.29","feb":"17.29","mar":"17.29","apr":"17.29","may":"17.29","jun":"18.23","jul":"18.23","aug":"18.23","sept":"-","oct":"-","nov":"-","dec":"-","average":"17.64"},{"no":"94","name":"ข้อต่อท่อ พีวีซี ข้องอ 90 องศา สำหรับใช้กับท่อรับแรงดัน เส้นผ่านศูนย์กลาง 1 1/2\" ตราท่อน้ำไทย","unit":"อัน","jan":"21.50","feb":"21.50","mar":"21.50","apr":"21.50","may":"21.50","jun":"22.90","jul":"22.90","aug":"22.90","sept":"-","oct":"-","nov":"-","dec":"-","average":"22.03"},{"no":"95","name":"ข้อต่อท่อ พีวีซี ข้องอ 90 องศา สำหรับใช้กับท่อรับแรงดัน เส้นผ่านศูนย์กลาง 2\" ตราท่อน้ำไทย","unit":"อัน","jan":"30.85","feb":"30.85","mar":"30.85","apr":"30.85","may":"30.85","jun":"35.52","jul":"35.52","aug":"35.52","sept":"-","oct":"-","nov":"-","dec":"-","average":"32.60"},{"no":"96","name":"ข้อต่อท่อ พีวีซี ข้องอ 90 องศา สำหรับใช้กับท่อรับแรงดัน เส้นผ่านศูนย์กลาง 2 1/2\" ตราท่อน้ำไทย","unit":"อัน","jan":"71.03","feb":"71.03","mar":"71.03","apr":"71.03","may":"71.03","jun":"74.77","jul":"74.77","aug":"74.77","sept":"-","oct":"-","nov":"-","dec":"-","average":"72.43"},{"no":"97","name":"ข้อต่อท่อ พีวีซี ข้องอ 90 องศา สำหรับใช้กับท่อรับแรงดัน เส้นผ่านศูนย์กลาง 3\" ตราท่อน้ำไทย","unit":"อัน","jan":"96.27","feb":"96.27","mar":"96.27","apr":"96.27","may":"96.27","jun":"96.73","jul":"96.73","aug":"96.73","sept":"-","oct":"-","nov":"-","dec":"-","average":"96.44"},{"no":"98","name":"ข้อต่อท่อ พีวีซี ข้องอ 90 องศา สำหรับใช้กับท่อรับแรงดัน เส้นผ่านศูนย์กลาง 4\" ตราท่อน้ำไทย","unit":"อัน","jan":"185.52","feb":"185.52","mar":"185.52","apr":"185.52","may":"185.52","jun":"185.52","jul":"185.52","aug":"185.52","sept":"-","oct":"-","nov":"-","dec":"-","average":"185.52"},{"no":"99","name":"ข้อต่อท่อ พีวีซี ข้องอ 90 องศา สำหรับใช้กับท่อรับแรงดัน เส้นผ่านศูนย์กลาง 1/2\" ตราเสือ","unit":"อัน","jan":"9.35","feb":"9.35","mar":"9.35","apr":"9.35","may":"11.21","jun":"11.21","jul":"9.35","aug":"9.35","sept":"-","oct":"-","nov":"-","dec":"-","average":"9.82"},{"no":"100","name":"ข้อต่อท่อ พีวีซี ข้องอ 90 องศา สำหรับใช้กับท่อรับแรงดัน เส้นผ่านศูนย์กลาง 3/4\" ตราเสือ","unit":"อัน","jan":"11.21","feb":"11.21","mar":"11.21","apr":"11.21","may":"12.15","jun":"12.15","jul":"11.21","aug":"11.21","sept":"-","oct":"-","nov":"-","dec":"-","average":"11.45"},{"no":"101","name":"ข้อต่อท่อ พีวีซี ข้องอ 90 องศา สำหรับใช้กับท่อรับแรงดัน เส้นผ่านศูนย์กลาง 1\" ตราเสือ","unit":"อัน","jan":"14.02","feb":"14.02","mar":"14.02","apr":"14.02","may":"14.95","jun":"14.95","jul":"14.02","aug":"14.02","sept":"-","oct":"-","nov":"-","dec":"-","average":"14.25"},{"no":"102","name":"ข้อต่อท่อ พีวีซี สามทาง 90 องศา สำหรับใช้กับท่อรับแรงดัน เส้นผ่าศูนย์กลาง 1/2\" ตราท่อน้ำไทย","unit":"อัน","jan":"6.08","feb":"6.08","mar":"6.08","apr":"6.08","may":"6.08","jun":"6.55","jul":"6.55","aug":"6.55","sept":"-","oct":"-","nov":"-","dec":"-","average":"6.26"},{"no":"103","name":"ข้อต่อท่อ พีวีซี สามทาง 90 องศา สำหรับใช้กับท่อรับแรงดัน เส้นผ่าศูนย์กลาง 3/4\" ตราท่อน้ำไทย","unit":"อัน","jan":"7.48","feb":"7.48","mar":"7.48","apr":"7.48","may":"7.48","jun":"8.42","jul":"8.42","aug":"8.42","sept":"-","oct":"-","nov":"-","dec":"-","average":"7.83"},{"no":"104","name":"ข้อต่อท่อ พีวีซี สามทาง 90 องศา สำหรับใช้กับท่อรับแรงดัน เส้นผ่าศูนย์กลาง 1\" ตราท่อน้ำไทย","unit":"อัน","jan":"14.49","feb":"14.49","mar":"14.49","apr":"14.49","may":"14.49","jun":"14.96","jul":"14.96","aug":"14.96","sept":"-","oct":"-","nov":"-","dec":"-","average":"14.67"},{"no":"105","name":"ข้อต่อท่อ พีวีซี สามทาง 90 องศา สำหรับใช้กับท่อรับแรงดัน เส้นผ่าศูนย์กลาง 1 1/4\" ตราท่อน้ำไทย","unit":"อัน","jan":"20.10","feb":"20.10","mar":"20.10","apr":"20.10","may":"20.10","jun":"22.90","jul":"22.90","aug":"22.90","sept":"-","oct":"-","nov":"-","dec":"-","average":"21.15"},{"no":"106","name":"ข้อต่อท่อ พีวีซี สามทาง 90 องศา สำหรับใช้กับท่อรับแรงดัน เส้นผ่าศูนย์กลาง 1 1/2\" ตราท่อน้ำไทย","unit":"อัน","jan":"29.44","feb":"29.44","mar":"29.44","apr":"29.44","may":"29.44","jun":"31.78","jul":"31.78","aug":"31.78","sept":"-","oct":"-","nov":"-","dec":"-","average":"30.32"},{"no":"107","name":"ข้อต่อท่อ พีวีซี สามทาง 90 องศา สำหรับใช้กับท่อรับแรงดัน เส้นผ่าศูนย์กลาง 2\" ตราท่อน้ำไทย","unit":"อัน","jan":"48.13","feb":"48.13","mar":"48.13","apr":"48.13","may":"48.13","jun":"48.13","jul":"48.13","aug":"48.13","sept":"-","oct":"-","nov":"-","dec":"-","average":"48.13"},{"no":"108","name":"ข้อต่อท่อ พีวีซี สามทาง 90 องศา สำหรับใช้กับท่อรับแรงดัน เส้นผ่าศูนย์กลาง 2 1/2\" ตราท่อน้ำไทย","unit":"อัน","jan":"105.61","feb":"105.61","mar":"105.61","apr":"105.61","may":"105.61","jun":"109.35","jul":"109.35","aug":"109.35","sept":"-","oct":"-","nov":"-","dec":"-","average":"107.01"},{"no":"109","name":"ข้อต่อท่อ พีวีซี สามทาง 90 องศา สำหรับใช้กับท่อรับแรงดัน เส้นผ่าศูนย์กลาง 3\" ตราท่อน้ำไทย","unit":"อัน","jan":"182.72","feb":"182.72","mar":"182.72","apr":"182.72","may":"182.72","jun":"183.18","jul":"183.18","aug":"183.18","sept":"-","oct":"-","nov":"-","dec":"-","average":"182.89"},{"no":"110","name":"ข้อต่อท่อ พีวีซี สามทาง 90 องศา สำหรับใช้กับท่อรับแรงดัน เส้นผ่าศูนย์กลาง 4\" ตราท่อน้ำไทย","unit":"อัน","jan":"395.80","feb":"395.80","mar":"395.80","apr":"395.80","may":"395.80","jun":"395.80","jul":"395.80","aug":"395.80","sept":"-","oct":"-","nov":"-","dec":"-","average":"395.80"},{"no":"111","name":"ท่อระบายน้ำคอนกรีตเสริมเหล็ก ปากลิ้นราง ชั้น 3 ยาว 1 เมตร ศก. 0.30 ม.","unit":"ท่อน","jan":"480.37","feb":"480.37","mar":"480.37","apr":"480.37","may":"480.37","jun":"519.63","jul":"519.63","aug":"519.63","sept":"-","oct":"-","nov":"-","dec":"-","average":"495.09"},{"no":"112","name":"ท่อระบายน้ำคอนกรีตเสริมเหล็ก ปากลิ้นราง ชั้น 3 ยาว 1 เมตร ศก. 0.60 ม.","unit":"ท่อน","jan":"789.72","feb":"789.72","mar":"789.72","apr":"789.72","may":"789.72","jun":"789.72","jul":"789.72","aug":"789.72","sept":"-","oct":"-","nov":"-","dec":"-","average":"789.72"},{"no":"113","name":"ท่อระบายน้ำคอนกรีตเสริมเหล็ก ปากลิ้นราง ชั้น 3 ยาว 1 เมตร ศก. 0.80 ม.","unit":"ท่อน","jan":"1,559.81","feb":"1,559.81","mar":"1,559.81","apr":"1,559.81","may":"1,559.81","jun":"1,559.81","jul":"1,559.81","aug":"1,559.81","sept":"-","oct":"-","nov":"-","dec":"-","average":"1,559.81"},{"no":"114","name":"ท่อระบายน้ำคอนกรีตเสริมเหล็ก ปากลิ้นราง ชั้น 3 ยาว 1 เมตร ศก. 1.00 ม .","unit":"ท่อน","jan":"2,340.19","feb":"2,340.19","mar":"2,340.19","apr":"2,340.19","may":"2,340.19","jun":"2,340.19","jul":"2,340.19","aug":"2,340.19","sept":"-","oct":"-","nov":"-","dec":"-","average":"2,340.19"},{"no":"115","name":"ท่อระบายน้ำคอนกรีตเสริมเหล็ก ปากลิ้นราง ชั้น 3 ยาว 1 เมตร ศก. 1.20 ม.","unit":"ท่อน","jan":"3,400.00","feb":"3,400.00","mar":"3,400.00","apr":"3,400.00","may":"3,400.00","jun":"3,400.00","jul":"3,400.00","aug":"3,400.00","sept":"-","oct":"-","nov":"-","dec":"-","average":"3,400.00"},{"no":"116","name":"ท่อระบายน้ำซีเมนต์ใยหิน ยาว 4 เมตร ศก. 10 ซม.","unit":"ท่อน","jan":"149.53","feb":"149.53","mar":"149.53","apr":"149.53","may":"149.53","jun":"149.53","jul":"140.19","aug":"140.19","sept":"-","oct":"-","nov":"-","dec":"-","average":"147.20"},{"no":"117","name":"ท่อระบายน้ำซีเมนต์ใยหิน ยาว 4 เมตร ศก. 15 ซม.","unit":"ท่อน","jan":"224.30","feb":"224.30","mar":"224.30","apr":"224.30","may":"224.30","jun":"224.30","jul":"196.26","aug":"196.26","sept":"-","oct":"-","nov":"-","dec":"-","average":"217.29"},{"no":"118","name":"ท่อระบายน้ำซีเมนต์ใยหิน ยาว 4 เมตร ศก. 20 ซม.","unit":"ท่อน","jan":"336.45","feb":"336.45","mar":"336.45","apr":"336.45","may":"336.45","jun":"336.45","jul":"252.34","aug":"252.34","sept":"-","oct":"-","nov":"-","dec":"-","average":"315.42"},{"no":"119","name":"ท่อระบายน้ำซีเมนต์ใยหิน ยาว 3 เมตร ศก. 10 ซม.","unit":"ท่อน","jan":"182.24","feb":"182.24","mar":"182.24","apr":"182.24","may":"182.24","jun":"182.24","jul":"182.24","aug":"182.24","sept":"-","oct":"-","nov":"-","dec":"-","average":"182.24"},{"no":"120","name":"ท่อระบายน้ำซีเมนต์ใยหิน ยาว 3 เมตร ศก. 15 ซม.","unit":"ท่อน","jan":"225.23","feb":"225.23","mar":"225.23","apr":"225.23","may":"225.23","jun":"225.23","jul":"225.23","aug":"225.23","sept":"-","oct":"-","nov":"-","dec":"-","average":"225.23"},{"no":"121","name":"ท่อระบายน้ำซีเมนต์ใยหิน ยาว 3 เมตร ศก. 20 ซม.","unit":"ท่อน","jan":"285.05","feb":"285.05","mar":"285.05","apr":"285.05","may":"285.05","jun":"285.05","jul":"285.05","aug":"285.05","sept":"-","oct":"-","nov":"-","dec":"-","average":"285.05"},{"no":"122","name":"มุ้งลวดอลูมิเนียม ขนาดกว้าง 90 ซม ยาว 30 เมตร สีขาว","unit":"ม้วน","jan":"1,588.79","feb":"1,588.79","mar":"1,588.79","apr":"1,588.79","may":"1,588.79","jun":"1,588.79","jul":"1,588.79","aug":"1,588.79","sept":"-","oct":"-","nov":"-","dec":"-","average":"1,588.79"},{"no":"123","name":"ลวดหนามเคลือบสังกะสี เบอร์ 15","unit":"กก.","jan":"172.90","feb":"172.90","mar":"172.90","apr":"172.90","may":"172.90","jun":"172.90","jul":"190.65","aug":"190.65","sept":"-","oct":"-","nov":"-","dec":"-","average":"177.34"},{"no":"124","name":"ลวดหนามเคลือบสังกะสี เบอร์ 14","unit":"กก.","jan":"175.39","feb":"178.50","mar":"178.50","apr":"178.50","may":"181.62","jun":"189.41","jul":"196.88","aug":"194.70","sept":"-","oct":"-","nov":"-","dec":"-","average":"184.19"},{"no":"125","name":"ลวดหนามเคลือบสังกะสี เบอร์ 12","unit":"กก.","jan":"212.15","feb":"212.15","mar":"212.15","apr":"212.15","may":"212.15","jun":"212.15","jul":"240.19","aug":"240.19","sept":"-","oct":"-","nov":"-","dec":"-","average":"219.16"},{"no":"126","name":"ลวดหนามเคลือบสังกะสี เบอร์ 18","unit":"กก.","jan":"210.28","feb":"210.28","mar":"210.28","apr":"210.28","may":"210.28","jun":"210.28","jul":"210.28","aug":"196.26","sept":"-","oct":"-","nov":"-","dec":"-","average":"208.53"},{"no":"127","name":"แผ่นฉนวนกันความร้อน ขนาด 66 ซม. x 4 ม. หนา 3 นิ้ว ตราช้าง","unit":"แผ่น","jan":"299.07","feb":"299.07","mar":"299.07","apr":"299.07","may":"299.07","jun":"359.81","jul":"359.81","aug":"359.81","sept":"-","oct":"-","nov":"-","dec":"-","average":"321.85"},{"no":"128","name":"กระเบื้องคอนกรีตมุงหลังคา ซีแพคโมเนีย ขนาด 33 x 42 ซม. สีแดง เทา อิฐ น้ำตาล ตราช้าง","unit":"แผ่น","jan":"14.02","feb":"14.02","mar":"14.02","apr":"14.02","may":"14.02","jun":"14.49","jul":"14.49","aug":"14.49","sept":"-","oct":"-","nov":"-","dec":"-","average":"14.20"},{"no":"129","name":"กระเบื้องคอนกรีตมุงหลังคา ลอนเอลาบานา ขนาด 33 x 42 ซม. สีอิฐ ตราช้าง","unit":"แผ่น","jan":"15.89","feb":"15.89","mar":"15.89","apr":"15.89","may":"15.89","jun":"15.89","jul":"15.89","aug":"-","sept":"-","oct":"-","nov":"-","dec":"-","average":"15.89"},{"no":"130","name":"กระเบื้องคอนกรีตมุงหลังคา ลอนเอลาบานา ขนาด 33 x 42 ซม. สีน้ำตาล ตราช้าง","unit":"แผ่น","jan":"15.89","feb":"15.89","mar":"15.89","apr":"15.89","may":"15.89","jun":"15.89","jul":"15.89","aug":"-","sept":"-","oct":"-","nov":"-","dec":"-","average":"15.89"},{"no":"131","name":"กระเบื้องคอนกรีตมุงหลังคา ซีแพคโมเนีย ขนาด 33 x 42 ซม. สีแดง ตราช้าง","unit":"แผ่น","jan":"15.89","feb":"15.89","mar":"15.89","apr":"15.89","may":"15.89","jun":"15.89","jul":"15.89","aug":"-","sept":"-","oct":"-","nov":"-","dec":"-","average":"15.89"},{"no":"132","name":"ครอบสันโค้งกระเบื้องคอนกรีต สีแดง เทา อิฐ น้ำตาล ตราช้าง","unit":"แผ่น","jan":"38.32","feb":"38.32","mar":"38.32","apr":"38.32","may":"38.32","jun":"42.06","jul":"42.06","aug":"43.93","sept":"-","oct":"-","nov":"-","dec":"-","average":"39.96"},{"no":"133","name":"ครอบข้างกระเบื้องคอนกรีต สีแดง เทา อิฐ น้ำตาล ตราช้าง","unit":"แผ่น","jan":"38.32","feb":"38.32","mar":"38.32","apr":"38.32","may":"38.32","jun":"42.06","jul":"42.06","aug":"43.93","sept":"-","oct":"-","nov":"-","dec":"-","average":"39.96"},{"no":"134","name":"ครอบข้างปิดชายกระเบื้องคอนกรีต สีแดง เทา อิฐ น้ำตาล ตราช้าง","unit":"แผ่น","jan":"50.47","feb":"50.47","mar":"50.47","apr":"50.47","may":"50.47","jun":"57.01","jul":"57.01","aug":"62.62","sept":"-","oct":"-","nov":"-","dec":"-","average":"53.62"},{"no":"135","name":"ครอบโค้งปิดจั่วกระเบื้องคอนกรีต สีแดง เทา อิฐ น้ำตาล ตราช้าง","unit":"แผ่น","jan":"63.08","feb":"63.08","mar":"63.08","apr":"63.08","may":"63.08","jun":"66.36","jul":"66.36","aug":"62.62","sept":"-","oct":"-","nov":"-","dec":"-","average":"63.84"},{"no":"136","name":"ครอบสันโค้งกระเบื้องคอนกรีตแม็กม่า สีแดง เทา อิฐ น้ำตาล ตรา ห้าห่วง","unit":"แผ่น","jan":"52.34","feb":"52.34","mar":"52.34","apr":"52.34","may":"52.34","jun":"52.34","jul":"52.34","aug":"52.34","sept":"-","oct":"-","nov":"-","dec":"-","average":"52.34"},{"no":"137","name":"ครอบข้างกระเบื้องคอนกรีตแม็กม่า สีแดง เทา อิฐ น้ำตาล ตรา ห้าห่วง","unit":"แผ่น","jan":"52.34","feb":"52.34","mar":"52.34","apr":"52.34","may":"52.34","jun":"52.34","jul":"52.34","aug":"52.34","sept":"-","oct":"-","nov":"-","dec":"-","average":"52.34"},{"no":"138","name":"ครอบข้างปิดชายกระเบื้องคอนกรีตแม็กม่า สีแดง เทา อิฐ น้ำตาล ตรา ห้าห่วง","unit":"แผ่น","jan":"59.81","feb":"59.81","mar":"59.81","apr":"59.81","may":"59.81","jun":"59.81","jul":"59.81","aug":"59.81","sept":"-","oct":"-","nov":"-","dec":"-","average":"59.81"},{"no":"139","name":"ครอบโค้งปิดจั่วกระเบื้องคอนกรีตแม็กม่า สีแดง เทา อิฐ น้ำตาล ตรา ห้าห่วง","unit":"แผ่น","jan":"74.77","feb":"74.77","mar":"74.77","apr":"74.77","may":"74.77","jun":"74.77","jul":"74.77","aug":"74.77","sept":"-","oct":"-","nov":"-","dec":"-","average":"74.77"},{"no":"140","name":"กระเบื้องลอนคู่ สีเทาซิเมนต์ ขนาด 50 x 120 x 0.5 ซม ตราช้าง","unit":"แผ่น","jan":"54.21","feb":"54.21","mar":"54.21","apr":"54.21","may":"54.21","jun":"54.67","jul":"54.67","aug":"54.21","sept":"-","oct":"-","nov":"-","dec":"-","average":"54.33"},{"no":"141","name":"กระเบื้องลอนคู่ สีเทาซิเมนต์ ขนาด 50 x 150 x 0.5 ซม ตราช้าง","unit":"แผ่น","jan":"70.09","feb":"70.09","mar":"70.09","apr":"70.09","may":"70.09","jun":"70.09","jul":"70.09","aug":"70.09","sept":"-","oct":"-","nov":"-","dec":"-","average":"70.09"},{"no":"142","name":"กระเบื้องลอนคู่ สีแดง เขียว ขนาด 50 x 120 x 0.5 ซม ตราช้าง","unit":"แผ่น","jan":"67.29","feb":"67.29","mar":"67.29","apr":"67.29","may":"67.29","jun":"67.29","jul":"67.29","aug":"67.29","sept":"-","oct":"-","nov":"-","dec":"-","average":"67.29"},{"no":"143","name":"กระเบื้องลอนคู่ สีเทาซิเมนต์ ขนาด 50 x 120 x0 .6 ซม. ตราช้าง","unit":"แผ่น","jan":"52.34","feb":"52.34","mar":"52.34","apr":"52.34","may":"52.34","jun":"56.07","jul":"57.01","aug":"57.01","sept":"-","oct":"-","nov":"-","dec":"-","average":"53.97"},{"no":"144","name":"กระเบื้องลอนคู่ สีแดง เขียว ขนาด 50 x 120 x0 .6 ซม. ตราช้าง","unit":"แผ่น","jan":"59.81","feb":"59.81","mar":"59.81","apr":"59.81","may":"59.81","jun":"62.62","jul":"63.55","aug":"63.55","sept":"-","oct":"-","nov":"-","dec":"-","average":"61.10"},{"no":"145","name":"กระเบื้องลอนคู่ สีแดง เขียว ขนาด 50 x 150 x0 .6 ซม. ตราช้าง","unit":"แผ่น","jan":"75.70","feb":"75.70","mar":"75.70","apr":"75.70","may":"75.70","jun":"75.70","jul":"76.64","aug":"76.64","sept":"-","oct":"-","nov":"-","dec":"-","average":"75.94"},{"no":"146","name":"ครอบสันโค้ง สีเทาซิเมนต์ ขนาด 23 x 50 x 0.5 ซม. ตราช้าง","unit":"แผ่น","jan":"56.07","feb":"56.07","mar":"56.07","apr":"56.07","may":"56.07","jun":"56.07","jul":"63.55","aug":"63.55","sept":"-","oct":"-","nov":"-","dec":"-","average":"57.94"},{"no":"147","name":"ครอบสันโค้ง สีแดง เขียว ขนาด 23 x 50 x 0.5 ซม. ตราช้าง","unit":"แผ่น","jan":"67.29","feb":"67.29","mar":"67.29","apr":"67.29","may":"67.29","jun":"67.29","jul":"67.29","aug":"65.42","sept":"-","oct":"-","nov":"-","dec":"-","average":"67.06"},{"no":"148","name":"ครอบข้าง สีเทาซิเมนต์ ขนาด 20 x 60 x 0.5 ซม. ตราช้าง","unit":"แผ่น","jan":"44.86","feb":"44.86","mar":"44.86","apr":"44.86","may":"44.86","jun":"44.86","jul":"48.60","aug":"48.60","sept":"-","oct":"-","nov":"-","dec":"-","average":"45.80"},{"no":"149","name":"ครอบข้าง สีแดง เขียว ขนาด 20 x 60 x 0.5 ซม. ตราช้าง","unit":"แผ่น","jan":"48.60","feb":"48.60","mar":"48.60","apr":"48.60","may":"48.60","jun":"48.60","jul":"56.07","aug":"56.07","sept":"-","oct":"-","nov":"-","dec":"-","average":"50.47"},{"no":"150","name":"ครอบมุม สีเทาซิเมนต์ ขนาด 50 x 45 x 0.5 ซม. ตราช้าง","unit":"แผ่น","jan":"42.06","feb":"42.06","mar":"42.06","apr":"42.06","may":"42.06","jun":"46.73","jul":"46.73","aug":"46.73","sept":"-","oct":"-","nov":"-","dec":"-","average":"43.81"},{"no":"151","name":"แผ่นไม้อัดยาง ชนิดใช้ภายใน เกรด A ขนาด 4' x 8' หนา 4 มม.","unit":"แผ่น","jan":"235.98","feb":"235.98","mar":"235.98","apr":"235.98","may":"235.98","jun":"231.31","jul":"245.33","aug":"245.33","sept":"-","oct":"-","nov":"-","dec":"-","average":"237.73"},{"no":"152","name":"แผ่นไม้อัดยาง ชนิดใช้ภายใน เกรด A ขนาด 4' x 8' หนา 10 มม.","unit":"แผ่น","jan":"420.56","feb":"420.56","mar":"420.56","apr":"420.56","may":"420.56","jun":"364.49","jul":"439.25","aug":"439.25","sept":"-","oct":"-","nov":"-","dec":"-","average":"418.22"},{"no":"153","name":"แผ่นไม้อัดยาง ชนิดใช้ภายใน เกรด A ขนาด 4' x 8' หนา 15 มม.","unit":"แผ่น","jan":"714.95","feb":"714.95","mar":"714.95","apr":"714.95","may":"714.95","jun":"714.95","jul":"742.99","aug":"742.99","sept":"-","oct":"-","nov":"-","dec":"-","average":"721.96"},{"no":"154","name":"แผ่นไม้อัดยาง ชนิดใช้ภายใน เกรด A ขนาด 4' x 8' หนา 20 มม.","unit":"","jan":"1,056.07","feb":"1,056.07","mar":"1,056.07","apr":"1,056.07","may":"1,056.07","jun":"1,056.07","jul":"1,196.26","aug":"1,196.26","sept":"-","oct":"-","nov":"-","dec":"-","average":"1,091.12"},{"no":"155","name":"แผ่นไม้อัดยาง ชนิดใช้ภายใน เกรด A ขนาด 4' x 8' หนา 4 มม.","unit":"แผ่น","jan":"220.56","feb":"225.23","mar":"225.23","apr":"225.23","may":"229.91","jun":"271.03","jul":"271.03","aug":"268.70","sept":"-","oct":"-","nov":"-","dec":"-","average":"242.12"},{"no":"156","name":"แผ่นไม้อัดยาง ชนิดใช้ภายใน เกรด A ขนาด 4' x 8' หนา 6 มม.","unit":"แผ่น","jan":"165.89","feb":"175.24","mar":"175.24","apr":"175.24","may":"182.25","jun":"366.83","jul":"362.15","aug":"358.88","sept":"-","oct":"-","nov":"-","dec":"-","average":"245.22"},{"no":"157","name":"แผ่นยิปซัม ธรรมดา ไม่มีอลูมิเนียมฟอยล์ ขนาด 120 x 240 ซม. หนา 9 มม.","unit":"แผ่น","jan":"142.53","feb":"142.53","mar":"142.53","apr":"142.53","may":"144.86","jun":"144.86","jul":"142.53","aug":"139.72","sept":"-","oct":"-","nov":"-","dec":"-","average":"142.76"},{"no":"158","name":"แผ่นยิปซัม ธรรมดา ไม่มีอลูมิเนียมฟอยล์ ขนาด 120 x 240 ซม. หนา 9 มม. ตราช้าง","unit":"แผ่น","jan":"165.42","feb":"165.42","mar":"165.42","apr":"165.42","may":"165.42","jun":"165.42","jul":"165.42","aug":"165.42","sept":"-","oct":"-","nov":"-","dec":"-","average":"165.42"},{"no":"159","name":"แผ่นยิปซัม ธรรมดา ไม่มีอลูมิเนียมฟอยล์ ขนาด 120 x 240 ซม. หนา 9 มม. ตราบีพีบี","unit":"แผ่น","jan":"159.81","feb":"159.81","mar":"159.81","apr":"159.81","may":"159.81","jun":"159.81","jul":"159.81","aug":"159.81","sept":"-","oct":"-","nov":"-","dec":"-","average":"159.81"},{"no":"160","name":"แผ่นยิปซัม ธรรมดา ไม่มีอลูมิเนียมฟอยล์ ขนาด 120 x 240 ซม. หนา 9 มม. ตรายิปรอค","unit":"แผ่น","jan":"138.32","feb":"138.32","mar":"138.32","apr":"138.32","may":"138.32","jun":"138.32","jul":"138.32","aug":"126.17","sept":"-","oct":"-","nov":"-","dec":"-","average":"136.80"},{"no":"161","name":"แผ่นยิปซัม ธรรมดา มีอลูมิเนียมฟอยล์ ขนาด 120 x 240 ซม. หนา 9 มม","unit":"แผ่น","jan":"228.97","feb":"233.64","mar":"233.64","apr":"233.64","may":"238.32","jun":"238.32","jul":"233.64","aug":"226.17","sept":"-","oct":"-","nov":"-","dec":"-","average":"233.29"},{"no":"162","name":"แผ่นยิปซัม ธรรมดา มีอลูมิเนียมฟอยล์ ขนาด 120 x 240 ซม. หนา 9 มม. ตราช้าง","unit":"แผ่น","jan":"244.86","feb":"244.86","mar":"244.86","apr":"244.86","may":"244.86","jun":"244.86","jul":"244.86","aug":"244.86","sept":"-","oct":"-","nov":"-","dec":"-","average":"244.86"},{"no":"163","name":"แผ่นยิปซัม ธรรมดา มีอลูมิเนียมฟอยล์ ขนาด 120 x 240 ซม. หนา 9 มม. ตรายิปรอค","unit":"แผ่น","jan":"205.61","feb":"205.61","mar":"205.61","apr":"205.61","may":"205.61","jun":"144.86","jul":"163.55","aug":"163.55","sept":"-","oct":"-","nov":"-","dec":"-","average":"187.50"},{"no":"164","name":"แผ่นยิปซัม ทนความชื้น ขนาด 120 x 240 ซม. หนา 9 มม. ตรายิปรอค","unit":"แผ่น","jan":"214.95","feb":"214.95","mar":"214.95","apr":"214.95","may":"214.95","jun":"214.95","jul":"214.95","aug":"60.75","sept":"-","oct":"-","nov":"-","dec":"-","average":"195.68"},{"no":"165","name":"เหล็กแผ่นเรียบดำ หนา 2 มม. ขนาด 4' x 8' หนัก 47 กก./แผ่น","unit":"แผ่น","jan":"1,774.77","feb":"1,774.77","mar":"1,774.77","apr":"1,774.77","may":"1,774.77","jun":"1,774.77","jul":"1,684.11","aug":"1,684.11","sept":"-","oct":"-","nov":"-","dec":"-","average":"1,752.11"},{"no":"166","name":"เหล็กแผ่นเรียบดำ หนา 3 มม. ขนาด 4' x 8' หนัก 70 กก./แผ่น","unit":"แผ่น","jan":"2,661.68","feb":"2,661.68","mar":"2,661.68","apr":"2,661.68","may":"2,661.68","jun":"2,661.68","jul":"2,525.23","aug":"2,525.23","sept":"-","oct":"-","nov":"-","dec":"-","average":"2,627.57"},{"no":"167","name":"เหล็กแผ่นเรียบดำ หนา 6 มม. ขนาด 4' x 8' หนัก 140 กก./แผ่น","unit":"แผ่น","jan":"5,359.81","feb":"5,359.81","mar":"5,359.81","apr":"5,359.81","may":"5,359.81","jun":"6,050.47","jul":"6,050.47","aug":"6,050.47","sept":"-","oct":"-","nov":"-","dec":"-","average":"5,618.81"},{"no":"168","name":"เหล็กแผ่นเรียบดำ หนา 9 มม. ขนาด 4' x 8' หนัก 210 กก./แผ่น","unit":"แผ่น","jan":"7,940.19","feb":"7,940.19","mar":"7,940.19","apr":"7,940.19","may":"7,940.19","jun":"8,989.72","jul":"8,989.72","aug":"8,989.72","sept":"-","oct":"-","nov":"-","dec":"-","average":"8,333.76"},{"no":"169","name":"กระจกใส หนา 5 มม.","unit":"ตร.ฟุต","jan":"116.82","feb":"121.50","mar":"121.50","apr":"121.50","may":"123.36","jun":"123.36","jul":"112.15","aug":"110.28","sept":"-","oct":"-","nov":"-","dec":"-","average":"118.81"},{"no":"170","name":"กระจกใส หนา 6 มม.","unit":"ตร.ฟุต","jan":"22.90","feb":"23.36","mar":"23.36","apr":"23.36","may":"23.36","jun":"23.36","jul":"23.36","aug":"22.43","sept":"-","oct":"-","nov":"-","dec":"-","average":"23.19"},{"no":"171","name":"กระจกสีตัดแสง สีชาอ่อน หนา 5 มม.","unit":"ตร.ฟุต","jan":"25.70","feb":"26.17","mar":"26.17","apr":"26.17","may":"26.17","jun":"26.17","jul":"26.17","aug":"25.23","sept":"-","oct":"-","nov":"-","dec":"-","average":"25.99"},{"no":"172","name":"กระจกสีตัดแสง สีชาอ่อน หนา 6 มม.","unit":"ตร.ฟุต","jan":"42.06","feb":"44.86","mar":"44.86","apr":"44.86","may":"46.73","jun":"46.73","jul":"44.86","aug":"42.99","sept":"-","oct":"-","nov":"-","dec":"-","average":"44.74"},{"no":"173","name":"กระเบื้องแผ่นเรียบ ขนาด 120 x 240 x 0.40 ซม. ตราช้าง","unit":"แผ่น","jan":"172.90","feb":"177.57","mar":"177.57","apr":"177.57","may":"179.44","jun":"179.44","jul":"177.57","aug":"171.03","sept":"-","oct":"-","nov":"-","dec":"-","average":"176.64"},{"no":"174","name":"กระเบื้องแผ่นเรียบ ขนาด 120 x 240 x 0.60 ซม. ตราช้าง","unit":"แผ่น","jan":"261.68","feb":"271.03","mar":"271.03","apr":"271.03","may":"275.70","jun":"275.70","jul":"271.03","aug":"261.68","sept":"-","oct":"-","nov":"-","dec":"-","average":"269.86"},{"no":"175","name":"ไม้ฝาไฟเบอร์ซีเมนต์ ขนาด 15 x 300 x 0.8 ซม. สีธรรมชาติ ตราช้าง","unit":"แผ่น","jan":"51.40","feb":"51.40","mar":"51.40","apr":"51.40","may":"51.40","jun":"57.94","jul":"60.75","aug":"72.90","sept":"-","oct":"-","nov":"-","dec":"-","average":"56.07"},{"no":"176","name":"ไม้ฝาไฟเบอร์ซีเมนต์ ขนาด 15 x 400 x 0.8 ซม. สีธรรมชาติ ตราช้าง","unit":"แผ่น","jan":"68.22","feb":"68.22","mar":"68.22","apr":"68.22","may":"68.22","jun":"68.22","jul":"72.90","aug":"-","sept":"-","oct":"-","nov":"-","dec":"-","average":"68.89"},{"no":"177","name":"กระเบื้องเคลือบปูพื้น ชนิดสีเรียบ ขนาด 8\" x 8\" ตราคัมพานา","unit":"ตร.ม.","jan":"139.25","feb":"139.25","mar":"139.25","apr":"139.25","may":"139.25","jun":"139.25","jul":"139.25","aug":"-","sept":"-","oct":"-","nov":"-","dec":"-","average":"139.25"},{"no":"178","name":"กระเบื้องเคลือบปูพื้น ชนิดสีเรียบ ขนาด 12\" x 12\" ตราคัมพานา","unit":"ตร.ม.","jan":"148.60","feb":"148.60","mar":"148.60","apr":"148.60","may":"148.60","jun":"148.60","jul":"148.60","aug":"-","sept":"-","oct":"-","nov":"-","dec":"-","average":"148.60"},{"no":"179","name":"กระเบื้องเคลือบปูพื้น ชนิดสีเรียบ ขนาด 8\" x 8\"","unit":"ตร.ม.","jan":"140.19","feb":"130.84","mar":"130.84","apr":"130.84","may":"135.51","jun":"135.51","jul":"130.84","aug":"121.50","sept":"-","oct":"-","nov":"-","dec":"-","average":"132.01"},{"no":"180","name":"กระเบื้องเคลือบปูพื้น ชนิดสีเรียบ ขนาด 12\" x 12\"","unit":"ตร.ม.","jan":"121.50","feb":"112.15","mar":"112.15","apr":"112.15","may":"114.02","jun":"121.50","jul":"121.50","aug":"112.15","sept":"-","oct":"-","nov":"-","dec":"-","average":"115.89"},{"no":"181","name":"กระเบื้องเคลือบปูพื้น ชนิดลวดลาย ขนาด 8\" x 8\" ตราคัมพานา","unit":"ตร.ม.","jan":"139.25","feb":"139.25","mar":"139.25","apr":"139.25","may":"139.25","jun":"139.25","jul":"139.25","aug":"-","sept":"-","oct":"-","nov":"-","dec":"-","average":"139.25"},{"no":"182","name":"กระเบื้องเคลือบปูพื้น ชนิดลวดลาย ขนาด 8\" x 8\"","unit":"ตร.ม.","jan":"126.17","feb":"130.84","mar":"130.84","apr":"130.84","may":"133.64","jun":"133.64","jul":"130.84","aug":"121.50","sept":"-","oct":"-","nov":"-","dec":"-","average":"129.79"},{"no":"183","name":"กระเบื้องเคลือบบุผนัง ชนิดสีเรียบ ขนาด 8\" x 10\" ตราคัมพานา","unit":"ตร.ม.","jan":"149.53","feb":"149.53","mar":"149.53","apr":"149.53","may":"149.53","jun":"149.53","jul":"149.53","aug":"149.53","sept":"-","oct":"-","nov":"-","dec":"-","average":"149.53"},{"no":"184","name":"กระเบื้องเคลือบบุผนัง ชนิดลวดลาย ขนาด 8\" x 8\" ตราลีลา","unit":"ตร.ม.","jan":"149.53","feb":"149.53","mar":"149.53","apr":"149.53","may":"149.53","jun":"149.53","jul":"149.53","aug":"149.53","sept":"-","oct":"-","nov":"-","dec":"-","average":"149.53"},{"no":"185","name":"กระเบื้องเคลือบบุผนัง ชนิดลวดลาย ขนาด 8\" x 10\" ตราลีลา","unit":"ตร.ม.","jan":"149.53","feb":"149.53","mar":"149.53","apr":"149.53","may":"149.53","jun":"149.53","jul":"149.53","aug":"149.53","sept":"-","oct":"-","nov":"-","dec":"-","average":"149.53"},{"no":"186","name":"กระเบื้องเคลือบบุผนัง ชนิดสีเรียบ ขนาด 8\" x 8\" ตราคัมพานา","unit":"ตร.ม.","jan":"139.25","feb":"139.25","mar":"139.25","apr":"139.25","may":"139.25","jun":"139.25","jul":"139.25","aug":"-","sept":"-","oct":"-","nov":"-","dec":"-","average":"139.25"},{"no":"187","name":"กระเบื้องเคลือบบุผนัง ชนิดลวดลาย ขนาด 8\" x 8\" ตราคัมพานา","unit":"ตร.ม.","jan":"139.25","feb":"139.25","mar":"139.25","apr":"139.25","may":"139.25","jun":"139.25","jul":"139.25","aug":"-","sept":"-","oct":"-","nov":"-","dec":"-","average":"139.25"},{"no":"188","name":"กระเบื้องเคลือบบุผนัง ชนิดลวดลาย ขนาด 8\" x 10\" ตราคอตโต้","unit":"ตร.ม.","jan":"139.25","feb":"139.25","mar":"139.25","apr":"139.25","may":"139.25","jun":"139.25","jul":"139.25","aug":"-","sept":"-","oct":"-","nov":"-","dec":"-","average":"139.25"},{"no":"189","name":"กระเบื้องเคลือบบุผนัง ชนิดเรียบ ขนาด 8\" x 10\" ตราคัมพานา","unit":"ตร.ม.","jan":"139.25","feb":"139.25","mar":"139.25","apr":"139.25","may":"139.25","jun":"139.25","jul":"139.25","aug":"-","sept":"-","oct":"-","nov":"-","dec":"-","average":"139.25"},{"no":"190","name":"ไม้แดง ไม่ไส ขนาด 2\" x 4\" ยาว 4 - 4.50 เมตร","unit":"ลบ.ฟ.","jan":"794.10","feb":"794.10","mar":"794.10","apr":"794.10","may":"794.10","jun":"922.43","jul":"922.43","aug":"819.63","sept":"-","oct":"-","nov":"-","dec":"-","average":"829.37"},{"no":"191","name":"ไม้แดง ไม่ไส ขนาด 2\" x 6\" ยาว 4 - 4.50 เมตร","unit":"ลบ.ฟ.","jan":"919.16","feb":"919.16","mar":"919.16","apr":"919.16","may":"919.16","jun":"1,149.66","jul":"1,149.66","aug":"551.41","sept":"-","oct":"-","nov":"-","dec":"-","average":"930.82"},{"no":"192","name":"ไม้ยาง ไม่ไส ขนาด 1/2\" x 6\" ยาว 4 - 4.50 เมตร","unit":"ลบ.ฟ.","jan":"819.72","feb":"819.72","mar":"819.72","apr":"819.72","may":"819.72","jun":"819.72","jul":"819.72","aug":"819.63","sept":"-","oct":"-","nov":"-","dec":"-","average":"819.71"},{"no":"193","name":"ไม้ยาง ไม่ไส ขนาด 1\" x 6\" ยาว 4 - 4.50 เมตร","unit":"ลบ.ฟ.","jan":"765.42","feb":"765.42","mar":"765.42","apr":"765.42","may":"765.42","jun":"765.42","jul":"765.42","aug":"765.42","sept":"-","oct":"-","nov":"-","dec":"-","average":"765.42"},{"no":"194","name":"ไม้ยาง ไม่ไส ขนาด 1\" x 8\" ยาว 4 - 4.50 เมตร","unit":"ลบ.ฟ.","jan":"676.64","feb":"676.64","mar":"676.64","apr":"676.64","may":"676.64","jun":"676.64","jul":"676.64","aug":"676.64","sept":"-","oct":"-","nov":"-","dec":"-","average":"676.64"},{"no":"195","name":"ไม้ยาง ไม่ไส ขนาด 1 1/2\" x 3\" ยาว 4 - 4.50 เมตร","unit":"ลบ.ฟ.","jan":"546.73","feb":"546.73","mar":"546.73","apr":"546.73","may":"546.73","jun":"546.73","jul":"546.73","aug":"303.27","sept":"-","oct":"-","nov":"-","dec":"-","average":"516.30"},{"no":"196","name":"ไม้กะบาก ไม่ไส ขนาด 1\" x 6\" ยาว 4 - 4.50 เมตร","unit":"ลบ.ฟ.","jan":"765.42","feb":"765.42","mar":"765.42","apr":"765.42","may":"765.42","jun":"765.42","jul":"765.42","aug":"438.79","sept":"-","oct":"-","nov":"-","dec":"-","average":"724.59"},{"no":"197","name":"ไม้กะบาก ไม่ไส ขนาด 1\" x 8\" ยาว 4 - 4.50 เมตร","unit":"ลบ.ฟ.","jan":"676.64","feb":"676.64","mar":"676.64","apr":"676.64","may":"676.64","jun":"697.20","jul":"697.20","aug":"403.74","sept":"-","oct":"-","nov":"-","dec":"-","average":"647.67"},{"no":"198","name":"สีน้ำมันเคลือบชนิดเงา ขนาด 3.785 ลิตร ตรา ที โอ เอ","unit":"กระป๋อง","jan":"579.44","feb":"579.44","mar":"579.44","apr":"579.44","may":"579.44","jun":"629.91","jul":"629.91","aug":"629.91","sept":"-","oct":"-","nov":"-","dec":"-","average":"598.37"},{"no":"199","name":"สีน้ำมันเคลือบชนิดด้าน ขนาด 3.785 ลิตร ตรา ที โอ เอ","unit":"กระป๋อง","jan":"672.90","feb":"672.90","mar":"672.90","apr":"672.90","may":"672.90","jun":"672.90","jul":"672.90","aug":"672.90","sept":"-","oct":"-","nov":"-","dec":"-","average":"672.90"},{"no":"200","name":"สีน้ำพลาสติก ทาภายใน ขนาด 3.785 ลิตร ตราซุปเปอร์โค้ท","unit":"กระป๋อง","jan":"299.07","feb":"299.07","mar":"299.07","apr":"299.07","may":"299.07","jun":"299.07","jul":"299.07","aug":"299.07","sept":"-","oct":"-","nov":"-","dec":"-","average":"299.07"},{"no":"201","name":"สีน้ำพลาสติก ทาภายใน ชนิดด้าน ขนาด 3.785 ลิตร ตรา ที โอ เอ (4 seasons)","unit":"กระป๋อง","jan":"338.32","feb":"338.32","mar":"338.32","apr":"338.32","may":"338.32","jun":"338.32","jul":"338.32","aug":"378.51","sept":"-","oct":"-","nov":"-","dec":"-","average":"343.34"},{"no":"202","name":"สีน้ำพลาสติก ทาภายใน ชนิดด้าน ขนาด 18.925 ลิตร ตรา ที โอ เอ (4 seasons)","unit":"กระป๋อง","jan":"1,395.33","feb":"1,395.33","mar":"1,395.33","apr":"1,395.33","may":"1,395.33","jun":"1,555.61","jul":"1,555.61","aug":"1,555.61","sept":"-","oct":"-","nov":"-","dec":"-","average":"1,455.44"},{"no":"203","name":"สีน้ำพลาสติก ทาภายนอก ชนิดด้าน ขนาด 3.785 ลิตร ตรา ที โอ เอ (4 seasons)","unit":"กระป๋อง","jan":"450.47","feb":"450.47","mar":"450.47","apr":"450.47","may":"450.47","jun":"550.47","jul":"550.47","aug":"550.47","sept":"-","oct":"-","nov":"-","dec":"-","average":"487.97"},{"no":"204","name":"สีน้ำพลาสติก ทาภายนอก ชนิดด้าน ขนาด 18.925 ลิตร ตรา ที โอ เอ (4 seasons)","unit":"กระป๋อง","jan":"1,950.47","feb":"1,950.47","mar":"1,950.47","apr":"1,950.47","may":"1,950.47","jun":"2,400.00","jul":"2,400.00","aug":"2,400.00","sept":"-","oct":"-","nov":"-","dec":"-","average":"2,119.04"},{"no":"205","name":"สีรองพื้นปูนใหม่ ขนาด 3.785 ลิตร ตราที โอ เอ","unit":"กระป๋อง","jan":"452.65","feb":"452.65","mar":"452.65","apr":"452.65","may":"452.65","jun":"492.21","jul":"484.42","aug":"484.42","sept":"-","oct":"-","nov":"-","dec":"-","average":"465.54"},{"no":"206","name":"น้ำมันเคลือบแข็ง ภายใน ขนาด 3.785 ลิตร ตราเครื่องบิน บี 52 (ยูนีเทน ยู 202)","unit":"กระป๋อง","jan":"803.43","feb":"803.43","mar":"803.43","apr":"803.43","may":"803.43","jun":"915.58","jul":"921.81","aug":"921.81","sept":"-","oct":"-","nov":"-","dec":"-","average":"847.04"},{"no":"207","name":"น้ำมันเคลือบแข็ง ภายใน ขนาด 3.785 ลิตร ตรา ที โอ เอ","unit":"กระป๋อง","jan":"1,050.47","feb":"1,050.47","mar":"1,050.47","apr":"1,050.47","may":"1,050.47","jun":"1,350.47","jul":"1,350.47","aug":"1,350.47","sept":"-","oct":"-","nov":"-","dec":"-","average":"1,162.97"},{"no":"208","name":"น้ำมันเคลือบแข็ง ภายนอก ขนาด 3.785 ลิตร ตราเครื่องบิน บี 52 (ยูนีเทน ยู 404)","unit":"กระป๋อง","jan":"1,158.88","feb":"1,158.88","mar":"1,158.88","apr":"1,158.88","may":"1,158.88","jun":"1,252.34","jul":"1,252.34","aug":"1,252.34","sept":"-","oct":"-","nov":"-","dec":"-","average":"1,193.93"},{"no":"209","name":"น้ำมันเคลือบแข็ง ภายนอก ขนาด 3.785 ลิตร ตรา ที โอ เอ","unit":"กระป๋อง","jan":"1,350.47","feb":"1,350.47","mar":"1,350.47","apr":"1,350.47","may":"1,350.47","jun":"1,350.47","jul":"1,350.47","aug":"1,350.47","sept":"-","oct":"-","nov":"-","dec":"-","average":"1,350.47"},{"no":"210","name":"แลกเกอร์ ชนิดเงา ขนาด 3.785 ลิตร ตรา ที โอ เอ","unit":"กระป๋อง","jan":"452.81","feb":"452.81","mar":"452.81","apr":"452.81","may":"452.81","jun":"452.81","jul":"452.81","aug":"452.81","sept":"-","oct":"-","nov":"-","dec":"-","average":"452.81"},{"no":"211","name":"แลกเกอร์ ชนิดด้าน ขนาด 3.785 ลิตร ตรา ที โอ เอ","unit":"กระป๋อง","jan":"466.36","feb":"466.36","mar":"466.36","apr":"466.36","may":"466.36","jun":"466.36","jul":"466.36","aug":"466.36","sept":"-","oct":"-","nov":"-","dec":"-","average":"466.36"},{"no":"212","name":"กระดาษทรายขัดไม้ เบอร์ 0 ขนาด 9 x 11 นิ้ว","unit":"โหล","jan":"76.94","feb":"78.50","mar":"78.50","apr":"78.50","may":"79.13","jun":"98.75","jul":"98.75","aug":"97.20","sept":"-","oct":"-","nov":"-","dec":"-","average":"85.78"},{"no":"213","name":"กระดาษทรายขัดไม้ เบอร์ 3 ขนาด 9 x 11 นิ้ว","unit":"โหล","jan":"114.96","feb":"114.96","mar":"114.96","apr":"114.96","may":"117.29","jun":"156.54","jul":"156.54","aug":"153.27","sept":"-","oct":"-","nov":"-","dec":"-","average":"130.44"},{"no":"214","name":"บานประตูไม้อัดสัก ชนิดใช้ภายใน หนา 3.5 ซม. ขนาด 70 x 200 ซม.","unit":"บาน","jan":"644.86","feb":"644.86","mar":"644.86","apr":"644.86","may":"649.53","jun":"663.55","jul":"663.55","aug":"654.21","sept":"-","oct":"-","nov":"-","dec":"-","average":"651.29"},{"no":"215","name":"บานประตูไม้อัดสัก ชนิดใช้ภายใน หนา 3.5 ซม. ขนาด 80 x 200 ซม.","unit":"บาน","jan":"626.17","feb":"626.17","mar":"626.17","apr":"626.17","may":"630.84","jun":"638.63","jul":"638.63","aug":"632.40","sept":"-","oct":"-","nov":"-","dec":"-","average":"630.65"},{"no":"216","name":"บานประตูไม้อัดสัก ชนิดใช้ภายนอก หนา 3.5 ซม. ขนาด 70 x 200 ซม.","unit":"บาน","jan":"1,551.40","feb":"1,551.40","mar":"1,551.40","apr":"1,551.40","may":"1,570.09","jun":"1,588.79","jul":"1,588.79","aug":"1,570.09","sept":"-","oct":"-","nov":"-","dec":"-","average":"1,565.42"},{"no":"217","name":"บานประตูไม้อัดสัก ชนิดใช้ภายนอก หนา 3.5 ซม. ขนาด 80 x 200 ซม.","unit":"บาน","jan":"1,257.01","feb":"1,266.36","mar":"1,266.36","apr":"1,266.36","may":"1,275.71","jun":"1,294.40","jul":"1,294.40","aug":"1,280.38","sept":"-","oct":"-","nov":"-","dec":"-","average":"1,275.12"},{"no":"218","name":"บานประตูไม้อัดยาง ชนิดใช้ภายใน หนา 3.5 ซม. ขนาด 70 x 200 ซม.","unit":"บาน","jan":"584.12","feb":"584.12","mar":"584.12","apr":"584.12","may":"584.12","jun":"616.83","jul":"616.83","aug":"616.83","sept":"-","oct":"-","nov":"-","dec":"-","average":"596.39"},{"no":"219","name":"บานประตูไม้อัดยาง ชนิดใช้ภายใน หนา 3.5 ซม. ขนาด 80 x 200 ซม.","unit":"บาน","jan":"588.79","feb":"588.79","mar":"588.79","apr":"588.79","may":"588.79","jun":"621.50","jul":"621.50","aug":"621.50","sept":"-","oct":"-","nov":"-","dec":"-","average":"601.06"},{"no":"220","name":"บานประตูไม้สัก บานทึบ ขนาด 80 x 200 ซม. กรอบบานขนาด 1 1/4\" x 4\" ลูกฟักหนา 1/2\"","unit":"บาน","jan":"3,177.57","feb":"3,177.57","mar":"3,177.57","apr":"3,177.57","may":"3,177.57","jun":"3,364.49","jul":"3,364.49","aug":"3,364.49","sept":"-","oct":"-","nov":"-","dec":"-","average":"3,247.67"},{"no":"221","name":"วงกบประตูไม้เนื้อแข็ง ไม่มีช่องแสง ขนาด 80 x 200 ซม. ขนาดไม้วงกบ 2\" x 4\"","unit":"ชุด","jan":"766.36","feb":"766.36","mar":"766.36","apr":"766.36","may":"766.36","jun":"794.39","jul":"794.39","aug":"794.39","sept":"-","oct":"-","nov":"-","dec":"-","average":"776.87"},{"no":"222","name":"วงกบหน้าต่างไม้เนื้อแข็ง ไม่มีช่องแสง ขนาด 60 x 110 ซม. ขนาดไม้วงกบ 2\" x 4\"","unit":"ชุด","jan":"607.48","feb":"607.48","mar":"607.48","apr":"607.48","may":"607.48","jun":"794.39","jul":"794.39","aug":"794.39","sept":"-","oct":"-","nov":"-","dec":"-","average":"677.57"},{"no":"223","name":"น๊อตหัวกลมสำหรับงานไม้ ขนาดเส้นผ่าศูนย์กลาง 9 มม. ยาว 6 นิ้ว","unit":"กก.","jan":"56.07","feb":"56.07","mar":"56.07","apr":"56.07","may":"56.07","jun":"56.07","jul":"56.07","aug":"56.07","sept":"-","oct":"-","nov":"-","dec":"-","average":"56.07"},{"no":"224","name":"ตะปูตอกไม้ ชนิดผอม ขนาด 3 นิ้ว","unit":"กก.","jan":"36.45","feb":"36.45","mar":"36.45","apr":"36.45","may":"36.45","jun":"56.07","jul":"56.07","aug":"56.07","sept":"-","oct":"-","nov":"-","dec":"-","average":"43.81"},{"no":"225","name":"ตะปูตอกไม้ ขนาด 1 1/2 นิ้ว บรรจุลัง นน.สุทธิ 17.6 กก. ตรามือ","unit":"ลัง","jan":"504.67","feb":"504.67","mar":"504.67","apr":"504.67","may":"504.67","jun":"813.08","jul":"813.08","aug":"813.08","sept":"-","oct":"-","nov":"-","dec":"-","average":"620.32"},{"no":"226","name":"ตะปูตอกไม้ ขนาด 2 นิ้ว บรรจุลัง นน.สุทธิ 17.6 กก. ตรามือ","unit":"ลัง","jan":"485.98","feb":"485.98","mar":"485.98","apr":"485.98","may":"485.98","jun":"785.05","jul":"785.05","aug":"785.05","sept":"-","oct":"-","nov":"-","dec":"-","average":"598.13"},{"no":"227","name":"ตะปูตอกคอนกรีต ขนาด 3\" - 4\"","unit":"กก.","jan":"57.48","feb":"57.48","mar":"57.48","apr":"57.48","may":"57.48","jun":"62.15","jul":"62.15","aug":"62.15","sept":"-","oct":"-","nov":"-","dec":"-","average":"59.23"},{"no":"228","name":"ตะปูตอกสังกะสี ขนาด 1 3/4\" เบอร์ 13","unit":"กก.","jan":"14.02","feb":"14.02","mar":"14.02","apr":"14.02","may":"14.02","jun":"18.69","jul":"18.69","aug":"18.69","sept":"-","oct":"-","nov":"-","dec":"-","average":"15.77"},{"no":"229","name":"ตะปูเกลียว ขนาด 3\"","unit":"ตัว","jan":"2.81","feb":"2.81","mar":"2.81","apr":"2.81","may":"2.81","jun":"2.81","jul":"2.81","aug":"2.81","sept":"-","oct":"-","nov":"-","dec":"-","average":"2.81"},{"no":"230","name":"ตะปูเกลียว ขนาด 4\"","unit":"ตัว","jan":"3.04","feb":"3.04","mar":"3.04","apr":"3.04","may":"3.04","jun":"3.04","jul":"3.04","aug":"3.04","sept":"-","oct":"-","nov":"-","dec":"-","average":"3.04"},{"no":"231","name":"ขอยึดกระเบื้อง ขนาด 6\"","unit":"อัน","jan":"3.04","feb":"3.04","mar":"3.04","apr":"3.04","may":"3.04","jun":"3.51","jul":"3.51","aug":"3.51","sept":"-","oct":"-","nov":"-","dec":"-","average":"3.22"},{"no":"232","name":"ขอยึดกระเบื้อง ขนาด 8\"","unit":"อัน","jan":"4.21","feb":"4.21","mar":"4.21","apr":"4.21","may":"4.21","jun":"4.44","jul":"4.44","aug":"4.44","sept":"-","oct":"-","nov":"-","dec":"-","average":"4.30"},{"no":"233","name":"บานพับหน้าต่างเหล็กเคลือบสังกะสี ปรับมุม ขนาด 10 นิ้ว","unit":"ชุด","jan":"42.06","feb":"42.06","mar":"42.06","apr":"42.06","may":"42.06","jun":"42.06","jul":"42.06","aug":"42.06","sept":"-","oct":"-","nov":"-","dec":"-","average":"42.06"},{"no":"234","name":"บานพับหน้าต่างเหล็กเคลือบสังกะสี ปรับมุม ขนาด 12 นิ้ว","unit":"ชุด","jan":"46.73","feb":"46.73","mar":"46.73","apr":"46.73","may":"46.73","jun":"46.73","jul":"46.73","aug":"46.73","sept":"-","oct":"-","nov":"-","dec":"-","average":"46.73"},{"no":"235","name":"กลอนอลูมิเนียม ขนาด 6 นิ้ว","unit":"อัน","jan":"18.69","feb":"18.69","mar":"18.69","apr":"18.69","may":"18.69","jun":"18.69","jul":"18.69","aug":"18.69","sept":"-","oct":"-","nov":"-","dec":"-","average":"18.69"},{"no":"236","name":"ปูนซีเมนต์ปอร์ตแลนด์ ปูนถุง ประเภท 1 ตราช้าง","unit":"ตัน","jan":"2,686.92","feb":"2,686.92","mar":"2,686.92","apr":"2,686.92","may":"2,686.92","jun":"3,196.26","jul":"3,196.26","aug":"3,046.73","sept":"-","oct":"-","nov":"-","dec":"-","average":"2,859.23"},{"no":"237","name":"ปูนซีเมนต์ผสม ปูนถุง บรรจุ 50 กก./ถุง ตราเสือ","unit":"ตัน","jan":"2,614.49","feb":"2,614.49","mar":"2,614.49","apr":"2,614.49","may":"2,614.49","jun":"2,710.28","jul":"2,710.28","aug":"2,672.90","sept":"-","oct":"-","nov":"-","dec":"-","average":"2,645.74"},{"no":"238","name":"ปูนซีเมนต์ผสม ปูนถุง บรรจุ 50 กก./ถุง ตรานกอินทรี","unit":"ตัน","jan":"3,014.02","feb":"3,014.02","mar":"3,014.02","apr":"3,014.02","may":"3,014.02","jun":"3,014.02","jul":"3,014.02","aug":"3,014.02","sept":"-","oct":"-","nov":"-","dec":"-","average":"3,014.02"},{"no":"239","name":"ฟลิ้นโค้ท เบอร์ 3 ขนาด 3.5 กก. ตราเชลล์","unit":"กระป๋อง","jan":"224.30","feb":"228.97","mar":"228.97","apr":"228.97","may":"233.64","jun":"233.64","jul":"233.64","aug":"224.30","sept":"-","oct":"-","nov":"-","dec":"-","average":"229.55"},{"no":"240","name":"แชลแลค ชนิดเกล็ด สีเหลือง","unit":"กก.","jan":"579.44","feb":"598.13","mar":"598.13","apr":"598.13","may":"605.61","jun":"605.61","jul":"598.13","aug":"588.79","sept":"-","oct":"-","nov":"-","dec":"-","average":"596.50"},{"no":"241","name":"น้ำยาประสานท่อพีวีซี ชนิดธรรมดา ขนาด 250 กรัม ตราท่อน้ำไทย","unit":"กระป๋อง","jan":"121.50","feb":"121.50","mar":"121.50","apr":"121.50","may":"121.50","jun":"121.50","jul":"121.50","aug":"121.50","sept":"-","oct":"-","nov":"-","dec":"-","average":"121.50"},{"no":"242","name":"น้ำยาประสานท่อพีวีซี ชนิดธรรมดา ขนาด 250 กรัม ตราเสือ","unit":"กระป๋อง","jan":"154.21","feb":"158.88","mar":"158.88","apr":"158.88","may":"163.55","jun":"163.55","jul":"158.88","aug":"154.21","sept":"-","oct":"-","nov":"-","dec":"-","average":"158.88"},{"no":"243","name":"ทรายหยาบ","unit":"ลบ.ม.","jan":"543.62","feb":"543.62","mar":"543.62","apr":"543.62","may":"543.62","jun":"543.62","jul":"543.62","aug":"543.62","sept":"-","oct":"-","nov":"-","dec":"-","average":"543.62"},{"no":"244","name":"ทรายละเอียด","unit":"ลบ.ม.","jan":"788.16","feb":"788.16","mar":"788.16","apr":"788.16","may":"792.83","jun":"823.99","jul":"819.31","aug":"813.08","sept":"-","oct":"-","nov":"-","dec":"-","average":"800.23"},{"no":"245","name":"หินย่อย เบอร์ 1 ราคา ณ โรงโม่","unit":"ลบ.ม.","jan":"467.29","feb":"467.29","mar":"467.29","apr":"467.29","may":"467.29","jun":"467.29","jul":"467.29","aug":"443.93","sept":"-","oct":"-","nov":"-","dec":"-","average":"464.37"},{"no":"246","name":"หินย่อย 3/4\" ราคา ณ โรงโม่","unit":"ลบ.ม.","jan":"467.29","feb":"467.29","mar":"467.29","apr":"467.29","may":"467.29","jun":"467.29","jul":"467.29","aug":"467.29","sept":"-","oct":"-","nov":"-","dec":"-","average":"467.29"},{"no":"247","name":"หินย่อย 3/8\" ราคา ณ โรงโม่","unit":"ลบ.ม.","jan":"420.56","feb":"420.56","mar":"420.56","apr":"420.56","may":"420.56","jun":"397.20","jul":"350.47","aug":"350.47","sept":"-","oct":"-","nov":"-","dec":"-","average":"400.12"},{"no":"248","name":"หินย่อย 1/2\" ราคา ณ โรงโม่","unit":"ลบ.ม.","jan":"467.29","feb":"467.29","mar":"467.29","apr":"467.29","may":"467.29","jun":"467.29","jul":"467.29","aug":"-","sept":"-","oct":"-","nov":"-","dec":"-","average":"467.29"},{"no":"249","name":"หินคลุก ราคา ณ โรงโม่","unit":"ลบ.ม.","jan":"420.56","feb":"420.56","mar":"420.56","apr":"420.56","may":"420.56","jun":"397.20","jul":"373.83","aug":"301.40","sept":"-","oct":"-","nov":"-","dec":"-","average":"396.90"},{"no":"250","name":"หินใหญ่ คละ ขนาด 15 - 30 ซม.","unit":"ลบ.ม.","jan":"841.12","feb":"841.12","mar":"841.12","apr":"841.12","may":"859.81","jun":"859.81","jul":"841.12","aug":"817.76","sept":"-","oct":"-","nov":"-","dec":"-","average":"842.87"},{"no":"251","name":"หินฝุ่น ราคา ณ โรงโม่","unit":"ลบ.ม.","jan":"420.56","feb":"420.56","mar":"420.56","apr":"420.56","may":"420.56","jun":"401.87","jul":"401.87","aug":"386.45","sept":"-","oct":"-","nov":"-","dec":"-","average":"411.62"},{"no":"252","name":"ก๊อกน้ำทองเหลือง (ผอม) ขนาด 1/2 นิ้ว","unit":"อัน","jan":"121.50","feb":"121.50","mar":"121.50","apr":"121.50","may":"128.51","jun":"133.18","jul":"133.18","aug":"133.18","sept":"-","oct":"-","nov":"-","dec":"-","average":"126.76"},{"no":"253","name":"ก๊อกน้ำทองเหลือง (อ้วน) ขนาด 1/2 นิ้ว","unit":"อัน","jan":"121.50","feb":"128.51","mar":"128.51","apr":"128.51","may":"134.12","jun":"142.53","jul":"142.53","aug":"142.53","sept":"-","oct":"-","nov":"-","dec":"-","average":"133.59"},{"no":"254","name":"ก๊อกน้ำทองเหลือง ขนาด 1/2 นิ้ว ตราซันวา","unit":"อัน","jan":"83.18","feb":"83.18","mar":"83.18","apr":"83.18","may":"83.18","jun":"83.18","jul":"83.18","aug":"139.25","sept":"-","oct":"-","nov":"-","dec":"-","average":"90.19"},{"no":"255","name":"ก๊อกน้ำทองเหลือง ขนาด 3/4 นิ้ว ตราซันวา","unit":"อัน","jan":"139.25","feb":"139.25","mar":"139.25","apr":"139.25","may":"139.25","jun":"139.25","jul":"139.25","aug":"157.94","sept":"-","oct":"-","nov":"-","dec":"-","average":"141.59"},{"no":"256","name":"ก๊อกน้ำบอลสนาม ขนาด 1/2 นิ้ว","unit":"อัน","jan":"105.14","feb":"109.82","mar":"109.82","apr":"109.82","may":"111.22","jun":"114.49","jul":"114.49","aug":"112.15","sept":"-","oct":"-","nov":"-","dec":"-","average":"110.87"},{"no":"257","name":"ก๊อกอ่างล้างหน้า แบบอะครีลิค ขนาด 1/2 นิ้ว","unit":"อัน","jan":"142.52","feb":"142.52","mar":"142.52","apr":"142.52","may":"144.39","jun":"147.20","jul":"147.20","aug":"142.52","sept":"-","oct":"-","nov":"-","dec":"-","average":"143.92"},{"no":"258","name":"สายไฟฟ้าเดินภายในอาคาร VAF สายแบนแกนคู่ ขนาด 2 x 1.5 ตร.มม. ยาว 100 ม.","unit":"ม้วน","jan":"1,401.87","feb":"1,355.14","mar":"1,355.14","apr":"1,355.14","may":"1,369.16","jun":"1,401.87","jul":"1,401.87","aug":"1,355.14","sept":"-","oct":"-","nov":"-","dec":"-","average":"1,374.42"},{"no":"259","name":"สายไฟฟ้าเดินภายในอาคาร VAF สายแบนแกนคู่ ขนาด 2 x 2.5 ตร.มม. ยาว 100 ม.","unit":"ม้วน","jan":"1,682.24","feb":"1,682.24","mar":"1,682.24","apr":"1,682.24","may":"1,682.24","jun":"1,682.24","jul":"1,682.24","aug":"1,682.24","sept":"-","oct":"-","nov":"-","dec":"-","average":"1,682.24"},{"no":"260","name":"สายไฟฟ้า VAF สายแบนแกนคู่ แรงดัน 300 โวลท์ ขนาด 2 x 4.0 ตร.มม. ยาว 100 เมตร","unit":"ม้วน","jan":"2,289.72","feb":"2,289.72","mar":"2,289.72","apr":"2,289.72","may":"2,289.72","jun":"2,364.49","jul":"2,364.49","aug":"2,364.49","sept":"-","oct":"-","nov":"-","dec":"-","average":"2,317.76"},{"no":"261","name":"สายเคเบิล THW สายกลมแกนเดี่ยว แรงดัน 750 โวลท์ ขนาด 1x1.5 ตร.มม. ยาว 100 ม.","unit":"ม้วน","jan":"607.48","feb":"607.48","mar":"607.48","apr":"607.48","may":"607.48","jun":"607.48","jul":"607.48","aug":"607.48","sept":"-","oct":"-","nov":"-","dec":"-","average":"607.48"},{"no":"262","name":"สายเคเบิล THW สายกลมแกนเดี่ยว แรงดัน 750 โวลท์ ขนาด 1x2.5 ตร.มม. ยาว 100 ม.","unit":"ม้วน","jan":"841.12","feb":"841.12","mar":"841.12","apr":"841.12","may":"841.12","jun":"841.12","jul":"841.12","aug":"841.12","sept":"-","oct":"-","nov":"-","dec":"-","average":"841.12"},{"no":"263","name":"สายเคเบิล THW สายกลมแกนเดี่ยว แรงดัน 750 โวลท์ ขนาด 1 x 4.0 ตร.มม. ยาว 100 เมตร","unit":"ม้วน","jan":"1,168.22","feb":"1,168.22","mar":"1,168.22","apr":"1,168.22","may":"1,168.22","jun":"1,168.22","jul":"1,168.22","aug":"1,168.22","sept":"-","oct":"-","nov":"-","dec":"-","average":"1,168.22"},{"no":"264","name":"สวิตช์ไฟฟ้าทางเดียว แบบฝังในผนัง ตราเนชั่นแนล","unit":"อัน","jan":"74.77","feb":"77.11","mar":"77.11","apr":"77.11","may":"78.04","jun":"79.44","jul":"79.44","aug":"77.11","sept":"-","oct":"-","nov":"-","dec":"-","average":"77.52"},{"no":"265","name":"สวิตช์ไฟฟ้าทางเดียว 15A 250V รุ่นฟลูคัลเลอร์ ซีรีส์ (WNG 5001-701) ตรา พานาโซนิค","unit":"อัน","jan":"32.71","feb":"32.71","mar":"32.71","apr":"32.71","may":"32.71","jun":"32.71","jul":"32.71","aug":"-","sept":"-","oct":"-","nov":"-","dec":"-","average":"32.71"},{"no":"266","name":"สวิตซ์ไฟฟ้า 3 ทาง 16A 250V รุ่นฟลูคัลเลอร์ วายด์ ซีรี่ส์ (WEG5002K) ตราพานาโซนิค","unit":"อัน","jan":"70.09","feb":"70.09","mar":"70.09","apr":"70.09","may":"70.09","jun":"70.09","jul":"70.09","aug":"-","sept":"-","oct":"-","nov":"-","dec":"-","average":"70.09"},{"no":"267","name":"เบรกเกอร์ ขนาด 10 A รุ่น HB BS1110YT ตราพานาโซนิค","unit":"อัน","jan":"129.91","feb":"129.91","mar":"129.91","apr":"129.91","may":"129.91","jun":"129.91","jul":"129.91","aug":"129.91","sept":"-","oct":"-","nov":"-","dec":"-","average":"129.91"},{"no":"268","name":"เบรกเกอร์ ขนาด 15 A รุ่น HB BS1111YT ตราพานาโซนิค","unit":"อัน","jan":"129.91","feb":"129.91","mar":"129.91","apr":"129.91","may":"129.91","jun":"129.91","jul":"129.91","aug":"129.91","sept":"-","oct":"-","nov":"-","dec":"-","average":"129.91"},{"no":"269","name":"เบรกเกอร์ ขนาด 20 A รุ่น HB BS1112YT ตราพานาโซนิค","unit":"อัน","jan":"120.56","feb":"120.56","mar":"120.56","apr":"120.56","may":"120.56","jun":"120.56","jul":"129.91","aug":"129.91","sept":"-","oct":"-","nov":"-","dec":"-","average":"122.90"},{"no":"270","name":"เบรกเกอร์ ขนาด 30 A รุ่น HB BS1113YT ตราพานาโซนิค","unit":"อัน","jan":"129.91","feb":"129.91","mar":"129.91","apr":"129.91","may":"129.91","jun":"129.91","jul":"129.91","aug":"129.91","sept":"-","oct":"-","nov":"-","dec":"-","average":"129.91"},{"no":"271","name":"เต้ารับ (เดี่ยว) แบบฝังในผนัง ตราเนชั่นแนล","unit":"อัน","jan":"32.71","feb":"32.71","mar":"32.71","apr":"32.71","may":"32.71","jun":"32.71","jul":"32.71","aug":"32.71","sept":"-","oct":"-","nov":"-","dec":"-","average":"32.71"},{"no":"272","name":"บัลลาสต์ 36/40 วัตต์ ตราฟิลิปส์","unit":"อัน","jan":"105.14","feb":"105.14","mar":"105.14","apr":"105.14","may":"107.48","jun":"107.48","jul":"107.48","aug":"107.48","sept":"-","oct":"-","nov":"-","dec":"-","average":"106.31"},{"no":"273","name":"สตาร์ทเตอร์ ขนาด 4-65 วัตต์ ตราฟิลิปส์","unit":"อัน","jan":"14.02","feb":"16.36","mar":"16.36","apr":"16.36","may":"16.83","jun":"17.29","jul":"17.29","aug":"17.76","sept":"-","oct":"-","nov":"-","dec":"-","average":"16.53"},{"no":"274","name":"หลอดไฟฟ้าฟลูออเรสเซนต์ แบบยาว ขนาด 36 วัตต์ ตราฟิลิปส์","unit":"หลอด","jan":"207.95","feb":"198.60","mar":"198.60","apr":"198.60","may":"203.28","jun":"184.58","jul":"168.22","aug":"86.45","sept":"-","oct":"-","nov":"-","dec":"-","average":"180.79"},{"no":"275","name":"หลอดไฟฟ้าฟลูออเรสเซนต์ แบบยาว ขนาด 36 วัตต์ ตราโตชิบา","unit":"หลอด","jan":"42.06","feb":"42.06","mar":"42.06","apr":"42.06","may":"42.06","jun":"42.06","jul":"42.06","aug":"42.06","sept":"-","oct":"-","nov":"-","dec":"-","average":"42.06"},{"no":"276","name":"หลอดไฟฟ้า แบบเกลียว ขนาด 60 วัตต์ ตราฟิลิปส์","unit":"ดวง","jan":"18.69","feb":"18.69","mar":"18.69","apr":"18.69","may":"18.69","jun":"18.69","jul":"18.69","aug":"18.69","sept":"-","oct":"-","nov":"-","dec":"-","average":"18.69"},{"no":"277","name":"หลอดตะเกียบ ขนาด 14 วัตต์ ตราฟิลิปส์","unit":"ดวง","jan":"64.49","feb":"64.49","mar":"64.49","apr":"64.49","may":"64.49","jun":"64.49","jul":"70.09","aug":"70.09","sept":"-","oct":"-","nov":"-","dec":"-","average":"65.89"},{"no":"278","name":"โถส้วมธรรมดานั่งยอง ไม่มีฐาน แบบราดน้ำ เคลือบขาว ตราอเมริกันแสตนดาร์ด รุ่น TF-100","unit":"ชิ้น","jan":"467.29","feb":"514.02","mar":"514.02","apr":"514.02","may":"518.69","jun":"514.02","jul":"514.02","aug":"495.33","sept":"-","oct":"-","nov":"-","dec":"-","average":"506.43"},{"no":"279","name":"ที่ปัสสาวะเซรามิกชาย ชนิดแขวนผนัง เคลือบขาว ตราอเมริกันแสตนดาร์ด รุ่น TF- 412","unit":"ชิ้น","jan":"1,448.60","feb":"514.02","mar":"514.02","apr":"514.02","may":"551.40","jun":"607.48","jul":"700.93","aug":"1,448.60","sept":"-","oct":"-","nov":"-","dec":"-","average":"787.38"},{"no":"280","name":"ที่ปัสสาวะเซรามิกชาย ชนิดแขวนผนัง เคลือบขาว ตรากะรัต รุ่น K-3200","unit":"ชิ้น","jan":"953.27","feb":"953.27","mar":"953.27","apr":"953.27","may":"953.27","jun":"953.27","jul":"953.27","aug":"962.62","sept":"-","oct":"-","nov":"-","dec":"-","average":"954.44"},{"no":"281","name":"อ่างล้างหน้าเซรามิก ชนิดแขวนผนัง เคลือบขาว ตราอเมริกันแสตนดาร์ด รุ่น TF- 911","unit":"ชิ้น","jan":"1,121.50","feb":"887.85","mar":"887.85","apr":"887.85","may":"901.87","jun":"901.87","jul":"887.85","aug":"869.16","sept":"-","oct":"-","nov":"-","dec":"-","average":"918.23"},{"no":"282","name":"อ่างล้างหน้าเซรามิก ชนิดแขวนผนัง เคลือบขาว ตรากะรัต รุ่น K-1210","unit":"ชิ้น","jan":"653.27","feb":"653.27","mar":"653.27","apr":"653.27","may":"653.27","jun":"653.27","jul":"653.27","aug":"653.27","sept":"-","oct":"-","nov":"-","dec":"-","average":"653.27"},{"no":"283","name":"ที่วางสบู่เซรามิก ชนิดฝังผนัง เคลือบขาว ตราอเมริกันแสตนดาร์ด รุ่น TF- 9000","unit":"ชิ้น","jan":"168.22","feb":"149.53","mar":"149.53","apr":"149.53","may":"154.21","jun":"158.88","jul":"158.88","aug":"149.53","sept":"-","oct":"-","nov":"-","dec":"-","average":"154.79"},{"no":"284","name":"ที่วางสบู่เซรามิก ชนิดฝังผนัง เคลือบขาว ตรากะรัต รุ่น K-504","unit":"ชิ้น","jan":"275.70","feb":"275.70","mar":"275.70","apr":"275.70","may":"275.70","jun":"275.70","jul":"275.70","aug":"275.70","sept":"-","oct":"-","nov":"-","dec":"-","average":"275.70"},{"no":"285","name":"ที่วางสบู่เซรามิก ชนิดฝังผนัง เคลือบขาว ตรากะรัต รุ่น K-595","unit":"ชิ้น","jan":"275.70","feb":"275.70","mar":"275.70","apr":"275.70","may":"275.70","jun":"275.70","jul":"275.70","aug":"275.70","sept":"-","oct":"-","nov":"-","dec":"-","average":"275.70"},{"no":"286","name":"ที่ใส่กระดาษชำระเซรามิก ชนิดฝังผนัง เคลือบขาว ตรากะรัต รุ่น K-596","unit":"ชิ้น","jan":"275.70","feb":"275.70","mar":"275.70","apr":"275.70","may":"275.70","jun":"275.70","jul":"275.70","aug":"275.70","sept":"-","oct":"-","nov":"-","dec":"-","average":"275.70"},{"no":"287","name":"ที่ใส่กระดาษชำระเซรามิก ชนิดฝังผนัง เคลือบขาว ตรากะรัต รุ่น K-512","unit":"ชิ้น","jan":"251.40","feb":"251.40","mar":"251.40","apr":"251.40","may":"251.40","jun":"251.40","jul":"251.40","aug":"251.40","sept":"-","oct":"-","nov":"-","dec":"-","average":"251.40"}]